Workbook

Sheet từ ghép n23
A1: 参加 | B1: THAM GIA | C1: さんか | D1: tham gia
A2: 参考 | B2: THAM KHẢO | C2: さんこう | D2: tham khảo
A3: 参戦 | B3: THAM CHIẾN | C3: さんせん | D3: tham chiến
A4: 乗車 | B4: THỪA XA | C4: じょうしゃ | D4: phương tiện giao thông
A5: 乗客 | B5: THỪA KHÁCH | C5: じょうきゃく | D5: hành khách
A6: 乾季 | B6: CAN QUÝ | C6: かんき | D6: mùa khô
A7: 乾杯 | B7: CAN BÔI | C7: かんぱい | D7: cạn ly
A8: 事件 | B8: SỰ KIỆN | C8: じけん | D8: sự kiện
A9: 事情 | B9: SỰ TÌNH | C9: じじょう | D9: tình trạng
A10: 事故 | B10: SỰ CỐ | C10: じこ | D10: Tai nạn
A11: 主人 | B11: CHỦ NHÂN | C11: しゅじん | D11: Người chồng
A12: 主義 | B12: CHỦ NGHĨA | C12: しゅぎ | D12: Chủ nghĩa
... A1612: 実験 | B1612: THỰC NGHIỆM | C1612: じっけん | D1612: Thực nghiệm, kinh nghiệm thực tế

Sheet N5
A1: 漢字 | B1: ひらがな | C1: Hán Việt | D1: Nghĩa | E1: Chưa thuộc | F1: Từ loại
A2: 私 | B2: わたし | C2: Tư | D2: Tôi | F2: N
A3: 私達 | B3: わたしたち | C3: Tư đạt | D3: Chúng tôi | F3: N
A4: 貴方 | B4: あなた | C4: Quý phương | D4: Bạn | F4: N
A5: 先生 | B5: せんせい | C5: Tiên sinh | D5: Cô, thầy giáo | F5: N
A6: 教師 | B6: きょうし | C6: Giáo sư | D6: Giáo viên | F6: N
A7: 実習生 | B7: じっしゅうせい | C7: Thực tập sinh | D7: Thực tập sinh | F7: N
A8: 研究者 | B8: けんきゅうしゃ | C8: Nghiên cứu giả | D8: Nhà nghiên cứu | F8: N
A9: 技術者 | B9: ぎじゅつしゃ | C9: Kỹ thuật giả | D9: Kỹ thuật viên | F9: N
A10: 留学生 | B10: りゅうがくせい | C10: Lưu học sinh | D10: Du học sinh | F10: N
A11: 学生 | B11: がくせい | C11: Học sinh | D11: Học sinh | F11: N
A12: 会社員/社員 | B12: かいしゃいん | C12: Hội xã viên | D12: Nhân viên công ty | F12: N
A13: 銀行員 | B13: ぎんこういん | C13: Ngân hàng viên | D13: Nhân viên ngân hàng | F13: N
... A24: 韓国 | B24: かんこく | C24: Hàn quốc | D24: Hàn Quốc | F24: N
A25: ベトナム | D25: Việt Nam | F25: N
A26: 日本 /にっぽん | B26: にほん | C26: Nhật bản | D26: Nhật Bản | F26: N
A27: 誰 | B27: だれ | C27: Thùy | D27: Ai | F27: N
A28: 本 | B28: ほん | C28: Bản | D28: Quyển sách | F28: N
A29: 辞書 | B29: じしょ | C29: Từ thư | D29: Từ điển | F29: N
A30: 雑誌 | B30: ざっし | C30: Tạp chí | D30: Tạp chí | F30: N
A31: 新聞 | B31: しんぶん | C31: Tân văn | D31: Báo | F31: N
A32: 紙 | B32: かみ | C32: Chỉ | D32: Giấy | F32: N
A33: 煙草 | B33: たばこ | C33: Yên thảo | D33: Thuốc lá | F33: N
A34: 灰皿 | B34: はいざら | C34: Hôi mãnh | D34: Gạt tàn thuốc lá | F34: N
A35: 箱 | B35: はこ | C35: Tương | D35: Hộp | F35: N
A36: 手紙 | B36: てがみ | C36: Thủ chỉ | D36: Thư | F36: N
A37: 手帳 | B37: てちょう | C37: Thủ trướng | D37: Sổ tay | F37: N
... A100: 一昨日 | B100: おととい | C100: Nhất tác minh | D100: Hôm kia | F100: N
A101: 昨日 | B101: きのう | D101: Hôm qua | F101: N
A102: 今日 | B102: きょう | D102: Hôm nay | F102: N
A103: 明日 | B103: あした | C103: Minh | D103: Ngày mai | F103: N
A104: 明後日 | B104: あっさて | C104: Minh hậu nhật | D104: Ngày kia | F104: N
A105: 今朝 | B105: けさ | C105: Kim triều | D105: Sáng nay | F105: N
A106: 今晩 | B106: こんばん | C106: Kim vãn | D106: Tối nay | F106: N
A107: 昼休み | B107: ひるやすみ | C107: Trú hưu | D107: Nghỉ trưa | F107: N
A108: 講義 | B108: こうぎ | C108: Giảng nghĩa | D108: Bài giảng | F108: N
A109: 日曜日 | B109: にちようび | C109: Nhật diệu | D109: Chủ nhật | F109: N
A110: 月曜日 | B110: けつようび | C110: Nguyệt | D110: Thứ 2 | F110: N
A111: 火曜日 | B111: かようび | C111: Hỏa | D111: Thứ 3 | F111: N
A112: 水曜日 | B112: すいようび | C112: Thủy | D112: Thứ 4 | F112: N
A113: 木曜日 | B113: もくようび | C113: Mộc | D113: Thứ 5 | F113: N
A114: 金曜日 | B114: きんようび | C114: Kim | D114: Thứ 6 | F114: N
A115: 土曜日 | B115: どようび | C115: Thổ | D115: Thứ 7 | F115: N
A116: 何曜日 | B116: なんようび | D116: Thứ mấy | F116: N
A117: 番号 | B117: ばんごう | C117: Phiên hiệu | D117: Số | F117: N
A118: 何番 | B118: なんばん | D118: Số mấy | F118: N
A119: 大変ですね | B119: たいへんですね | C119: Đại biến | D119: Vất vả quá nhỉ. | F119: N
A120: お願いします | B120: おねがいします | C120: Nguyện | D120: Làm ơn... | F120: N
A121: 行く | B121: いく | C121: Hành | D121: Đi | F121: V
A122: 来る | B122: くる | C122: Lai | D122: Đến | F122: V
A123: 帰る | B123: かえる | C123: Quy | D123: Về | F123: V
A124: 学校 | B124: がっこう | C124: Học hiệu | D124: Trường học | F124: N
A125: 小学校 | B125: しょうがっこう | C125: Tiểu học hiệu | D125: Trường cấp 1 | F125: N
A126: 中学校 | B126: ちゅうがっこう | C126: Trung học hiệu | D126: Trường cấp 2 | F126: N
A127: 高校 | B127: こうこう | C127: Cao hiệu | D127: Trường cấp 3 | F127: N
A128: 市場 | B128: いちば | C128: Thị trường | D128: Chợ | E128: 1 | F128: N
A129: 駅 | B129: えき | C129: Dịch | D129: Nhà ga | F129: N
A130: 工場 | B130: こうじょう | C130: Công trường | D130: Công trường | F130: N
A131: 企業 | B131: きぎょう | C131: Xí nghiệp | D131: Xí nghiệp | E131: 1 | F131: N
A132: ～屋 | B132: ～や | C132: ốc | D132: Hiệu, cửa hàng | F132: N
A133: 故郷 | B133: ふるさと/こきょう | C133: Cố hương | D133: Quê hương | E133: 1 | F133: N
A134: 公園 | B134: こうえん | C134: Công viên | D134: Công viên | F134: N
A135: 空港 | B135: くうこう | C135: Không cảng | D135: Sân bay | F135: N
A136: 飛行機 | B136: ひこうき | C136: Phi hành cơ | D136: Máy bay | F136: N
A137: 船 | B137: ふね | C137: Thuyền | D137: Thuyền | F137: N
A138: 電車 | B138: でんしゃ | C138: Điện xa | D138: Tàu điện | F138: N
A139: 新幹線 | B139: しんかんせん | C139: Tân cán tuyến | D139: Tàu siêu tốc | F139: N
A140: 地下鉄 | B140: ちかてつ | C140: Địa hạ thiết | D140: Tàu điện ngầm | F140: N
A141: 普通 | B141: ふつう | C141: Phổ thông | D141: Tàu thường | F141: N
A142: 急行 | B142: きゅうこう | C142: Cấp hành | D142: Tàu nhanh | F142: N
A143: 特急 | B143: とっきゅう | C143: Đặc cấp | D143: Tàu tốc hành | F143: N
A144: 自転車 | B144: じてんしゃ | C144: Tự chuyển xa | D144: Xe đạp | F144: N
A145: 歩いて | B145: あるいて | C145: Bộ | D145: Đi bộ | F145: N
... A147: 友達 | B147: ともだち | C147: Hữu đạt | D147: Bạn bè | F147: N
A148: 恋人 | B148: こいびと | C148: Luyến | D148: Người yêu | E148: 1 | F148: N
A149: 彼 | B149: かれ | C149: Bỉ | D149: Anh ấy | F149: N
A150: 彼女 | B150: かのじょ | C150: Bỉ nữ | D150: Cô ấy | F150: N
A151: 家族 | B151: かぞく | C151: Gia tộc | D151: Gia đình | F151: N
A152: 一人で | B152: ひとりで | D152: Một mình | F152: N
A153: 先週/先月/去年 | C153: Chu, nguyệt, niên | D153: Tuần/Tháng/Năm trước | F153: N
A154: 今週/今月/今年 | D154: Tuần/Tháng/Năm nay | F154: N
A155: 来週/来月/来年 | D155: Tuần/Tháng/Năm sau | F155: N
A156: 週末 | B156: しゅうまつ | C156: Chu mạt | D156: Cuối tuần | F156: N
A157: 誕生日 | B157: たんじょうび | C157: Đản sinh nhật | D157: Ngày sinh nhật | F157: N
A158: ～番線 | B158: ～ばんせん | C158: Phiên tuyến | D158: Chuyến số - | F158: N
A159: 次の | B159: つぎの | C159: Thứ | D159: Tiếp theo | F159: N
A160: 食べる | B160: たべる | C160: Thực | D160: Ăn | F160: V
A161: 飲む | B161: のむ | C161: Ẩm | D161: Uống | F161: V
A162: 吸う | B162: すう | C162: Hấp | D162: Hút | F162: V
A163: 見る | B163: みる | C163: Kiến | D163: Xem, nhìn | F163: V
A164: 聞く | B164: きく | C164: Văn | D164: Nghe, hỏi | F164: V
A165: 書く | B165: かく | C165: Thư | D165: Viết, vẽ | F165: V
A166: 読む | B166: よむ | C166: Độc | D166: Đọc | F166: V
A167: 買う | B167: かう | C167: Mãi | D167: Mua | F167: V
A168: 撮る | B168: とる | C168: Toát | D168: Chụp | E168: 1 | F168: V
A169: 会う | B169: あう | C169: Hội | D169: Gặp | F169: V
A170: 実習する | B170: じっしゅうする | C170: Thực tập | D170: Thực hành | E170: 1 | F170: V
A171: ご飯 | B171: ごはん | C171: Phạm | D171: Cơm, bữa ăn | F171: N
A172: 朝ご飯 | B172: あさごはん | C172: triều phạm | D172: Cơm sáng | F172: N
A173: 昼ご飯 | B173: ひるごはん | C173: trú phạm | D173: Cơm trưa | F173: N
...

Sheet N4
A1: 漢字 | B1: ひらがな | C1: Hán Việt | D1: Nghĩa | E1: Chưa thuộc | F1: Từ loại
A2: 診る | B2: みる | C2: Chẩn | D2: Xem, khám bệnh | F2: V
A3: 探す、捜す | B3: さがす | C3: Thám, sưu | D3: Tìm, tìm kiếm | F3: V
A4: 遅れる | B4: おくれる | C4: Trì | D4: Chậm, muộn | F4: V
A5: 間に合う | B5: まにあう | C5: Gian hợp | D5: Kịp | F5: V
A6: やる | D6: Làm | F6: V
A7: 参加する | B7: さんかする | C7: Tham gia | D7: Tham gia, dự | F7: V
A8: 申し込む | B8: もうしこむ | C8: Thân nhập | D8: Đăng kí | F8: A
A9: 都合が良い | B9: つごうがいい | C9: Đô hợp lương | D9: Có time | F9: A
A10: 都合が悪い | B10: つごうがわるい | C10: Đô hợp ác | D10: Không có time | F10: A
A11: 気分が良い | B11: きぶんがいい | C11: Khí phân lương | D11: Cảm thấy tốt | F11: A
A12: 気分が悪い | B12: きぶんがわるい | C12: Khí phân ác | D12: Cảm thấy không tốt | F12: A
A13: 新聞社 | B13: しんぶんしゃ | C13: Tân văn xã | D13: Tòa soạn báo | F13: N
A14: 柔道 | B14: じゅうどう | C14: Nhu đạo | D14: Môn nhu đạo | F14: N
A15: 運動会 | B15: うんどうかい | C15: vận động hội | D15: Hội thi thể thao | F15: N
A16: 場所 | B16: ばしょ | C16: Trường sở | D16: Địa điểm | F16: N
A17: ～弁 | B17: べん | C17: Biện, biền | D17: Giọng, tiếng ~ | F17: N
A18: 今度 | B18: こんど | C18: Kim độ | D18: Lần tới | F18: N
... A44: 聞こえる | B44: きこえる | C44: Văn | D44: Nghe thấy | F44: V
A45: できます | D45: Được xây dựng | F45: V
A46: 開く | B46: ひらく | C46: Khai | D46: Mở (lớp học) | F46: V
A47: 鳥 | B47: とり | C47: Điểu | D47: Chim | F47: N
A48: 声 | B48: こえ | C48: Thanh | D48: Tiếng, giọng (人)
A49: 波 | B49: なみ | C49: Ba | D49: Sóng biển
A50: 花火 | B50: はなび | C50: Hoa hỏa | D50: Pháo hoa
A51: 景色 | B51: けしき | C51: Cảnh sắc | D51: Phong cảnh(風景phong cảnh )
A52: 昼間 | B52: ひるま | C52: Trú gian | D52: Time ban ngày
A53: 昔 | B53: むかし | C53: Tích | D53: Ngày xưa
A54: 道具 | B54: どうぐ | C54: Đạo cụ | D54: Dụng cụ, công cụ
A55: 自動販売機 | B55: じどうはんばいき | C55: Tự động phiến mại cơ | D55: Máy bán hàng tự động
A56: 通信販売 | B56: つうしんはんばい | C56: Thông tín phiến mại | D56: Thương mại viễn thông
A57: 台所 | B57: だいどころ | C57: Đài sở | D57: Bếp
A58: ～教室 | B58: きょうしつ | C58: Giáo thất | D58: Lớp học
A59: ～後 | B59: ご | C59: Hậu | D59: Sau ~
... A61: 他の | B61: ほかの | C61: Tha | D61: Khác ngoài ra
A62: はっきり | D62: Rõ, rõ ràng
A63: 殆ど | B63: ほとんど | C63: Đãi | D63: Hầu như, hầu hết
A64: 日曜大工 | B64: にちようだいく | C64: Nhật diệu đại công | D64: Thợ mộc chủ nhật
A65: 本棚 | B65: ほんだな | C65: Bản bằng | D65: Giá sách
A66: 夢 | B66: ゆめ | C66: Mộng | D66: Giấc mơ
A67: 家 | B67: うち／いえ | C67: Gia | D67: Nhà
A68: 素晴らしい | B68: すばらしい | C68: Tố tình | D68: Tuyệt vời
A69: 子供達 | B69: こどもたち | C69: Tử cung đạt | D69: bọn Trẻ con
A70: 大好き（な） | B70: だいすき | C70: Đại hảo | D70: Rất thích
A71: 漫画 | B71: まんが | C71: Man/mạn họa/hoạch | D71: Truyện tranh
A72: 主人公 | B72: しゅじんこう | C72: Chủ nhân công | D72: Nhân vật chính
A73: 形 | B73: かたち | C73: Hình | D73: Hình dạng
A74: 不思議（な） | B74: ふしぎ | C74: Bất tư nghị | D74: Bí ẩn, kì thú
... A87: 通う | B87: かよう | C87: Thông | D87: Đi đi lại lại
A88: メモします | D88: Ghi chép
A89: 真面目 | B89: まじめ | C89: Chân diện mục | D89: Nghiêm túc
A90: 熱心 | B90: ねっしん | C90: Nhiệt tâm | D90: Nhiệt tình
A91: 優しい | B91: やさしい | C91: Ưu | D91: Hiền lành
A92: 偉い | B92: えらい | C92: Vĩ | D92: Vĩ đại
A93: 丁度いい | B93: ちょうどいい | C93: Đinh độ | D93: Vừa đủ, vừa đúng
A94: 習慣 | B94: しゅうかん | C94: Tập quán | D94: Tập quán
A95: 経験 | B95: けいけん | C95: Kinh nghiệm | D95: Kinh nghiệm
A96: 力 | B96: ちから | C96: Lực | D96: Sức lực công suất máy
A97: 人気 | B97: にんき | C97: Nhân khí | D97: Được hâm mộ
A98: 形 | B98: かたち | C98: Hình | D98: Hình dáng
A99: 色 | B99: いろ | C99: Sắc | D99: Màu sắc
A100: 味 | B100: あじ | C100: Vị | D100: Vị
... A116: 大抵 | B116: たいてい | C116: Đại để | D116: Thông thường nói chung
A117: それに | D117: Thêm nữa
A118: それで | D118: Thế nên
A119: 会話 | B119: かいわ | C119: Hội thoại | D119: Hội thoại
A120: おしゃべりする | D120: Nói chuyện
A121: お知らせ | B121: おしらせ | C121: Tri | D121: Bản thông báo
A122: 日にち | B122: ひにち | C122: Nhật | D122: Ngày
A123: 土 | B123: ど | C123: Thổ | D123: Thứ bảy
A124: 体育館 | B124: たいいくかん | C124: Thể dục quán | D124: Nhà tập thể dục
A125: 無料 | B125: むりょう | C125: Vô liệu | D125: Miễn phí
A126: 開く | B126: あく | C126: Khai | D126: Mở
A127: 閉まる | B127: しまる | C127: Bế | D127: Đóng
A128: 電気がつく | B128: でんきがつく | C128: điện khí | D128: Sáng
A129: 消える | B129: きえる | C129: Tiêu | D129: Tắt
A130: が込む | B130: こむ | C130: Nhập | D130: Đông, tắc
A131: がすく | D131: Vắng, thoáng
A132: 壊れる | B132: こわれる | C132: Hoại | D132: Hỏng
A133: 割れる | B133: われる | C133: Cát | D133: Vỡ
A134: 折れる | B134: おれる | C134: Triết | D134: Gãy, gập
A135: 破れる | B135: やぶれる | C135: Phá | D135: Rách
A136: 汚れる | B136: よごれる | C136: Ô | D136: Bẩn
A137: 付く | B137: つく | C137: Phó | D137: Có gắn dính
A138: 外れる | B138: はずれる | C138: Ngoại | D138: Tuột, bung tháo ra
A139: 止まる | B139: とまる | C139: Chỉ | D139: Dừng
A140: 間違える | B140: まちがえる | C140: Gian vi | D140: Nhầm, sai
A141: 落とす | B141: おとす | C141: Lạc | D141: Đánh rơi v+: làm gì đó sai sót
A142: 掛かる | B142: かかる | C142: Quải | D142: Khóa
A143: 皿 | B143: さら | C143: Mãnh | D143: Đĩa
... A150: ～辺 | B150: へん | C150: biên | D150: ~ xung quanh
A151: このくらい | D151: Khoảng ngần này
A152: お先に どうぞ | B152: おさきにどうぞ | C152: Tiên | D152: Xin mời đi trước
A153: 今の電車 | B153: いまのでんしゃ | C153: kim điện xa | D153: Đoàn tàu vừa rồi
A154: 忘れ物 | B154: わすれもの | C154: Vong vật | D154: Đồ để quên
A155: ～側 | B155: がわ | C155: Trắc | D155: Phía~, bên~
A156: 覚えていない | B156: おぼえていない | C156: Giác | D156: Tôi không nhớ
A157: 網棚 | B157: あみだな | C157: Võng bằng | D157: Giá lưới/hành lý
A158: 確か | B158: たしか | C158: Xác | D158: Nếu không nhầm thì chắc chắn là
A159: 地震 | B159: じしん | C159: Địa chấn | D159: Động đất
...

Sheet ngữ pháp n4
A1: 第２６課
A2: 1
A3: V
A4: Aい Thể thường
A5: んです
A6: Aな Thể thường
A7: N ～だ à な
A10: ＊ Ý nghĩa: (nhấn mạnh ý muốn nói, muốn hỏi; dùng trong văn nói nhiều)
A11: ＊ Cách cấu tạo:
A13: Động từ dạng ngắn V る･V ない･V た
A14: Tính từ đuôi i ～い
A15: んです。
A16: Tính từ đuôi na ～な
A17: Danh từ
... A50: どうして 遅れたんですか。Tai sao anh lại đến muộn thế?
A52: 16
A53: _x000C_ FPT University Tiếng Nhật cơ sở 3
A54: Japanese Language Training Division Giải thích văn phạm
A55: * Chú ý: Đôi khi ．～んですか biểu thị sự ngạc nhiên, mối nghi ngờ hay sự tò mò sâu sắc. Tuy nhiên,
A56: nếu không dùng đúng thì có thể làm tổn thương người nghe. Vì thế nên cẩn thận khi dùng.
A57: しゃちょう かえ
A59: × 社 長 、帰らないんですか。Anh không về sao, giám đốc?
A61: (à Biểu hiện này có hàm ý trách móc, dễ dẫn đến thất lễ)
A62: しゃちょう かえ
A64: ○ 社 長 、帰りませんか。Anh không về sao, giám đốc?
A67: (2) Trong câu trần thuật: 「～んです。」
A68: Biểu hiện này thường dùng trong những trường hợp sau:
A69: a) Khi trả lời câu hỏi tại sao giống như ý C ở phần trên. (phía sau không còn から nữa)
... A105: * Chú ý: ～ていただけませんか chứ không phải là ～ていただきませんか。
A108: 17
A109: _x000C_ FPT University Tiếng Nhật cơ sở 3
A110: Japanese Language Training Division Giải thích văn phạm
A111: Ví dụ:
A112: に ほ ん ご てがみ か み
A114: 日本語で 手紙を 書いたんですが、見て いただけませんか。
A116: Tôi đã viết 1 bức thư bằng tiếng Nhật, anh/chị xem giúp tôi được không ạ?
A117: き つか かた わ おし
A119: コピー機の 使い方が 分からないんですが、教えて いただけませんか。
A121: Tôi không biết cách sử dụng máy photo, anh/chị chỉ giúp tôi được không ạ?
A124: 2.2 (cách hỏi cách làm, xin lời khuyên,
A125: ～んですが、V たらいいですか。
A126: sự chỉ dẫn )
... A149: Anh/chị hãy hỏi chị Nga phòng khảo thí.
A154: 18
A155: _x000C_ FPT University Tiếng Nhật cơ sở 3
A156: Japanese Language Training Division Giải thích văn phạm
A158: だい か
A160: 第２７課
A161: か のうけい
A163: I. Động từ thể khả năng.（可能形）
A164: 1. Cách chia
A165: *Nhóm I: Là các động từ có vần [ i ] đứng trước ます。Để chuyển sang động từ thể khả năng chỉ cần
A166: chuyển [ i ] thành [ e ].
A167: ～ ます 可能形（かのうけい）
A168: およぎ ます およげ ます
A169: よみ ます よめ ます
... A198: F 私は 日本語 が 話せます。Tôi có thể nói tiếng Nhật
A201: 19
A202: _x000C_ FPT University Tiếng Nhật cơ sở 3
A203: Japanese Language Training Division Giải thích văn phạm
A204: ひとり びょういん い
A206: 2. 一人で 病 院へ 行きますか。Bạn đi một mình đến bệnh viên à?
A207: ひとり びょういん い
A209: F 一人で 病 院へ 行けますか。Bạn có thể đi một mình đến bệnh viện không?
A211: 3. Cách dùng: Giống như cách dùng của「V ることができます」học ở bài 18.
A213: a) Dùng để chỉ khả năng của ai đó có thể làm được gì.
A214: わたし かんじ よ
A216: Ví dụ: 私は 漢字が 読めます。
A217: Tôi có thể đọc được chữ Hán.
A218: わたし かんじ よ
... A259: Vì không có đài nên không thể nghe được nhạc.
A264: 20
A265: _x000C_ FPT University Tiếng Nhật cơ sở 3
A266: Japanese Language Training Division Giải thích văn phạm
A268: III. ～まだ 「V khả năng」～ません (cách nói chưa thể làm được gì)
A269: ＊ Ý nghĩa: Chưa thể (làm gì)
A270: ＊ Cách dùng: thể hiện 1 việc trong thời điểm nói thì chưa thể làm được nhưng sẽ cố gắng để sau
A271: này có thể thực hiện được
A272: Ví dụ:
A273: にほん うた うた
A275: 日本の歌が まだ 歌えません。Tôi chưa thể hát được bài hát Nhật
A276: に ほ ん ご じょうず はな
A278: 日本語が まだ 上手に 話せません。Tôi chưa thể nói giỏi tiếng Nhật được.
A281: IV. ～しか ～ません
... A312: Tenis thì tôi chơi được nhưng trượt tuyết thì không
A315: 21
A316: _x000C_ FPT University Tiếng Nhật cơ sở 3
A317: Japanese Language Training Division Giải thích văn phạm
A320: VI. N1 に N2 が できます
A321: ＊ Ý nghĩa: Ở N1 có N2 được hoàn thành
A322: ＊ Cách dùng: dùng để thể hiện sự hoàn thành của sự vật.
A323: Chú ý: Trợ từ cho danh từ chỉ nơi chốn trong mẫu câu này là [に]
A324: えき まえ おお
A326: Ví dụ: 駅の前に 大きいスーパーが できました。
A328: Trước cửa nhà ga, một siêu thị lớn đã được xây xong.
A329: おおさか あたら くうこう
A331: 大阪に 新 しい 空港が できました。
A333: Ở Osaka một sân bay mới đã hoàn thành.
A338: 22
A339: _x000C_ FPT University Tiếng Nhật cơ sở 3
...

Sheet N3
A1: STT | B1: 漢字 | C1: Hán Việt | D1: ひらがな | E1: Nghĩa | F1: Chưa thuộc | G1: Từ loại
A2: 1 | B2: 男性 | C2: Nam tính | D2: だんせい | E2: Nam giới
A3: 2 | B3: 女性 | C3: Nữ tính | D3: じょせい | E3: Nữ giới
A4: 3 | B4: 理想 | C4: Lý tưởng | D4: りそう | E4: Lý tưởng
A5: 4 | B5: 高齢 | C5: Cao linh | D5: こうれい | E5: Cao tuổi
A6: 5 | B6: 年上 | C6: Niên thượng | D6: としうえ | E6: Hơn tuổi
A7: 6 | B7: 目上 | C7: Mục thượng | D7: めうえ | E7: Người trên
A8: 7 | B8: 敬語 | C8: Kính ngữ | D8: けいご | E8: Kính ngữ
A9: 8 | B9: 先輩 | C9: Tiền bối | D9: せんぱい | E9: Tiền bối
A10: 9 | B10: 後輩 | C10: Hậu bối | D10: こうはい | E10: Hậu bối
A11: 10 | B11: 職場 | C11: Chức trường | D11: しょくば | E11: Nơi làm việc
A12: 11 | B12: 上司 | C12: Thượng ty | D12: じょうし | E12: Cấp trên
A13: 12 | B13: 決定 | C13: Quyết định | D13: けってい | E13: Quyết định
... A87: 87 | B87: 約束する | C87: Ước thúc | D87: やくそくする | E87: Lời hứa
A88: 88 | B88: おしゃべりする | E88: Nói chuyện
A89: 89 | B89: 怒る | C89: Nộ | D89: おこる | E89: Tức giận
A90: 90 | B90: 遠慮する | C90: Viễn lự | D90: えんりょ | E90: Ngại ngần
A91: 91 | B91: 我慢する | C91: Ngã mạn | D91: がまんする | E91: Chịu đựng
A92: 92 | B92: 迷惑する | C92: Mê hoặc | D92: めいわくする | E92: Làm phiền
A93: 93 | B93: 捨てる | C93: Vứt | D93: すてる | E93: Vứt
A94: 94 | B94: 希望 | C94: Hi vọng | D94: きぼう | E94: Hi vọng
A95: 95 | B95: 夢 | C95: Mộng | D95: ゆめ | E95: Giấc mơ, ước mơ
A96: 96 | B96: 怖い | C96: Bố trong khủng bố | D96: こわい | E96: Đáng sợ
A97: 97 | B97: 賛成する | C97: Tán thành | D97: さんせいする | E97: Tán thành
A98: 98 | B98: 挙げる | C98: Cử | D98: あげる | E98: Giơ tay
A99: 99 | B99: 反対する | C99: Phản đối | D99: はんたいする | E99: Phản đối
A100: 100 | B100: 想像する | C100: Tưởng tượng | D100: そうぞう | E100: Tưởng tượng
... A243: 243 | B243: 離す | C243: Ly | D243: はなす | E243: Để xa ra, làm tránh ra
A244: 244 | B244: ぶつかる | E244: Bị đâm
A245: 245 | B245: ぶつける | E245: Đâm vào
A246: 246 | B246: 涙 | C246: Lệ | D246: なみだ | E246: Nước mắt châu lệ nước mắt
A247: 247 | B247: 溢れる | C247: Dật | D247: こぼれる | E247: Tràn ra ngập tràn đầy
A248: 248 | B248: 溢す | C248: Dật | D248: こぼす | E248: Làm tràn ra
A249: 249 | B249: 拭く | C249: Thức | D249: ふく | E249: Lau, chùi, gạt
A250: 250 | B250: 片付く | C250: Phiến phó | D250: かたづく | E250: Ngăn nắp
A251: 251 | B251: 片付ける | C251: Phiến phó | D251: かたづける | E251: Dọn dẹp
A252: 252 | B252: 包む | C252: Bao | D252: つつむ | E252: Bọc
A253: 253 | B253: 貼る | C253: Thiếp | D253: はる | E253: Dán
A254: 254 | B254: 無くなる | C254: Vô | D254: なくなる | E254: Bị mất
A255: 255 | B255: 無くす | C255: Vô | D255: なくす | E255: Làm mất
A256: 256 | B256: 足りる | C256: Túc | D256: たりる | E256: Đủ
A257: 257 | B257: 収入 | C257: Thu nhập | D257: しゅうにゅう | E257: Thu nhập
... A331: 331 | B331: 正直（な） | C331: Chính trực | D331: しょうじき | E331: Trung thực
A332: 332 | B332: けち（な） | E332: Kiệt xỉ
A333: 333 | B333: 我儘（な） | C333: Ngã tận | D333: わがまま | E333: Ích kỉ
A334: 334 | B334: 積極的（な） | C334: Tích cực tính | D334: せっきょくてき | E334: Tính tích cực
A335: 335 | B335: 消極的（な） | C335: Tiêu cực tính | D335: しょうきょくてき | E335: Tính tiêu cực
A336: 336 | B336: 満足（な） | C336: Mãn túc | D336: まんぞく | E336: Mãn nguyện
A337: 337 | B337: 不満（な） | C337: Bất mãn | D337: ふまん | E337: Bất mãn
A338: 338 | B338: 不安（な） | C338: Bất an | D338: ふあん | E338: Bất an
A339: 339 | B339: 大変（な） | C339: Đại biến | D339: たいへん | E339: Vất vả
A340: 340 | B340: 無理（な） | C340: Vô lý | D340: むり | E340: Vô lý quá sức quá khả năng
A341: 341 | B341: 不注意（な） | C341: Bất chú ý | D341: ふちゅうい | E341: Không chú ý
A342: 342 | B342: 楽（な） | C342: Lạc | D342: らく | E342: Thoải mái, nhàn hạ
A343: 343 | B343: 面倒（な） | C343: Diện đảo | D343: めんどう | E343: Phiền hà, quấy rầy
A344: 344 | B344: 手続き | C344: Thủ tục | D344: てつづき | E344: Thủ tục
... A629: 631 | B629: 激しい | C629: Kích | D629: はげしい | E629: Mãnh liệt
A630: 632 | B630: そっくり（な） | E630: Giống
A631: 633 | B631: 急（な） | C631: cấp | D631: きゅう | E631: Gấp
A632: 634 | B632: 適当（な） | C632: Thích đương | D632: てきとう | E632: Thích hợp, vừa phải
A633: 635 | B633: 特別（な） | C633: Đặc biệt | D633: とくべつ | E633: Đặc biệt
A634: 636 | B634: 完全（な） | C634: Hoàn toàn | D634: かんぜん | E634: Hoàn toàn
A635: 637 | B635: 盛ん（な） | C635: Thịnh | D635: さかん | E635: Thịnh vượng
A636: 638 | B636: 様々（な） | C636: Dạng | D636: さまざま | E636: Nhiều loại
A637: 639 | B637: 可能（な） | C637: Khả năng | D637: かのう | E637: Khả năng
A638: 640 | B638: 不可能（な） | C638: Bất khả năng | D638: ふかのう | E638: Không khả thi
A639: 641 | B639: 基本的（な） | C639: Cơ bản đích | D639: きほんてき | E639: Tính cơ bản
A640: 642 | B640: 国際的（な） | C640: Quốc tế đích | D640: こくさいてき | E640: Tính quốc tế
A641: 643 | B641: ばらばら（な） | E641: Bừa bộn, lung tung
A642: 644 | B642: ぼろぼろ（な） | E642: Rách nát
A643: 645 | B643: 読書する | C643: Độc thư | D643: どくしょ | E643: Đọc sách
A644: 646 | B644: 演奏 | C644: Diễn tẫu | D644: えんそう | E644: Trình diễn, biểu diễn
A645: 647 | B645: 芸術 | C645: Nghệ thuật | D645: げいじゅつ | E645: Nghệ thuật
A646: 648 | B646: 検査する | C646: Kiểm tra | D646: ちょうさする | E646: Kiểm tra
A647: 649 | B647: 胃 | C647: Vị | D647: い | E647: Dạ dày
A648: 650 | B648: 血液 | C648: Huyết dịch | D648: けつえき | E648: Máu
A649: 651 | B649: 流れる | C649: Lưu | D649: ながれる | E649: Chảy, trôi đi
A650: 652 | B650: 治療する | C650: Trị liệu | D650: ちりょうする | E650: Trị liệu
A651: 653 | B651: 症状 | C651: Chứng trạng | D651: しょうじょう | E651: Triệu chứng
A652: 654 | B652: 鼻水 | C652: Tị thủy | D652: はなみず | E652: Nước mũi
A653: 655 | B653: 予防する | C653: Dự phòng | D653: よぼうする | E653: Dự phòng
A654: 656 | B654: 栄養 | C654: Vinh dưỡng | D654: えいよう | E654: Dinh dưỡng
... A824: 829 | B824: 時間 | C824: thời gian | D824: じかん | E824: thời gian
B825: 現在 | C825: hiện tại | D825: げんざい | E825: hiện tai
B826: 将来の夢 | C826: tương lai mộng | D826: しょうらいのゆめ | E826: ước mơ của tương lai
B827: 早朝 | C827: tảo triều | D827: そうちょう | E827: sáng sớm
B828: 昼間は暖かい | C828: trú gian noãn | D828: ひるまはあたたかい | E828: sự ấm áp của buổi trưa
B829: にっちゅう | C829: nhật trung | D829: にっちゅう | E829: ban ngày
B830: 夜中 | C830: dạ trung | D830: やちゅう | E830: ban đêm
B831: 真夜中 | C831: chân dạ trung | D831: まよなか | E831: nữa đêm
B832: 深夜 | C832: thâm dạ | D832: しんや | E832: nửa đêm
B833: 平日 | C833: bình nhật | D833: へいじつ | E833: ngày thường
B834: 休日 | C834: hưu nhật | D834: きゅうじつ | E834: ngày nghỉ
B835: 祝日 | C835: lễ nhật | D835: しゅくじつ | E835: ngày lễ
B836: 年末年始 | C836: niên mạt niên thủy | D836: ねんまつねんし | E836: đầu năm cuối năm
... B894: 晩ごはん | C894: văn | D894: ばんごはん | E894: bữa tối
B895: おやつ | E895: đồ nhắm đồ ăn vặt
B896: 夜食 | C896: dạ thưc | D896: やしょく | E896: ăn đêm
B897: 弁当 | C897: biện dương | D897: べんとう | E897: cơm hộp
B898: 定食 | C898: định thực | D898: ていしょく | E898: suất ăn
...

Sheet ngữ pháp n3
A1: 1.[Ngữ pháp N4] 受身形: Thể bị động
A2: A. Cách chia động từ thể bị động (受身：うけみ) từ thể từ điển:
A3: 1. Động từ nhóm 1: Chuyển đuôi う → あ + れる
A4: Ví dụ: 話す（はなす）→ 話される、言う（いう）→ 言われる、書く（かく）→ 書かれる
A5: 2. Động từ nhóm 2: Bỏ đuôi る → られる
A6: Ví dụ: 食べる（たべる）→ 食べられる、見る（みる）→ 見られる、教える（おしえる）→教えられる
A7: * Dạng bị động của động từ nhóm 2 giống với cách chia thể khả năng.
A8: 3. Động từ nhóm 3 (bất quy tắc)
A9: する → される 来る（くる）→ 来られる（こられる）→ giống với thể khả năng
A10: B. Cấu trúc:
A11: 1. Bị động trực tiếp (chỉ có 1 tân ngữ)
A12: Dạng chủ động: A は B を + động từ chủ động.
... A170:  [Chủ ngữ] + は/が + động từ kính ngữ
AL171: Khiêm Nhường Ngữ
A172: Làm＿します | AL172: いたします
A173: Có Mặt＿います | AL173: おります
A174: Đi＿行きます Đến ＿来ます | AL174: まいります うかがいます
A175: Xem＿見ます | AL175: はいけんします
A176: Nói＿言います | AL176: もうしあげます
A177: Ăn＿食べます Uống＿飲みます | AL177: いただきます
A178: Cho＿くれます
A179: Biết＿しります | AL179: ぞんじます ぞんじあげます
AL181: ご＋V+します お＋V+します
A182: Ko Dùng Với V 1 Âm Tiết | AL182: 会います＿Gặp àおめにかかり ます
AL183: 聞きます＿Hỏi àうかがいます
AL184: あげます＿Tặng àさしあげます
AL185: 見せます＿Cho Xem àおめにかけま
AL186: す
AL187: ありますàござ います
A189: Câu ví dụ:
A190: ① 山田さんは おそばを 召し上がりました。Anh Yamada đã ăn mì soba.
A191: ② 田中先生は いらっしゃいますか。Thầy Tanaka có ở đây không ạ?
A192: ③ 社長（しゃちょう）は ゴルフを なさいます。Giám đốc chơi golf.
A193: ④ アンさんは インドへ 出張（しゅっちょう）なさいます。Anh An sẽ đi công tác ở Ấn Độ.
A194: 2. Với những động từ không có dạng kính ngữ đặc biệt (ngoài mục 1 ở trên):
A195: Mẫu câu 1: [Chủ ngữ] + は/が + お + động từ thể ます(bỏ ます) + に なります。
A196: * Lưu ý: Mẫu câu 1 này không dùng với động từ nhóm 3 và những động từ nhóm 2 chỉ có 1 âm tiết phía trước đuôi 「る」 như 「いる」、「出る（でる）」、「着る（きる）」
A197: ① 先生は もう おかえり に なりました。
A198: → Thầy giáo đã về rồi.
A199: ② 部長（ぶちょう）は たばこを お吸(す)いに なりません。
A200: → Trưởng phòng không hút thuốc.
... A2105: bản thân quyết định. (Xem lại bài: ～ことにする）

Sheet N2
A1: Hán Tự | B1: Cách Đọc | C1: Ý Nghĩa | D1: Âm Hán
A2: 人生 | B2: じんせい | C2: Cuộc sống | D2: =VLOOKUP(A2,'N2.for ref'!B$2:E$1266,3,0) -> NHÂN SINH
A3: 人間 | B3: にんげん | C3: Nhân gian | D3: =VLOOKUP(A3,'N2.for ref'!B$2:E$1266,3,0) -> NHÂN GIAN
A4: 人 | B4: ひと | C4: Người | D4: =VLOOKUP(A4,'N2.for ref'!B$2:E$1266,3,0) -> NHÂN
A5: 祖先 | B5: そせん | C5: Tổ tiên | D5: =VLOOKUP(A5,'N2.for ref'!B$2:E$1266,3,0) -> TỔ TIÊN
A6: 親戚 | B6: しんせき | C6: Họ hàng | D6: =VLOOKUP(A6,'N2.for ref'!B$2:E$1266,3,0) -> THÂN THÍCH
A7: 夫婦 | B7: ふうふ | C7: Vợ chồng | D7: =VLOOKUP(A7,'N2.for ref'!B$2:E$1266,3,0) -> PHU PHỤ
A8: 長男 | B8: ちょうなん | C8: Trưởng nam | D8: =VLOOKUP(A8,'N2.for ref'!B$2:E$1266,3,0) -> TRƯỞNG NAM
A9: 主人 | B9: しゅじん | C9: Chủ cửa hàng, chồng | D9: =VLOOKUP(A9,'N2.for ref'!B$2:E$1266,3,0) -> CHỦ NHÂN
A10: 双子 | B10: ふたご | C10: Sinh đôi | D10: =VLOOKUP(A10,'N2.for ref'!B$2:E$1266,3,0) -> SONG TỬ
A11: 迷子 | B11: まいご | C11: Trẻ bị lạc | D11: =VLOOKUP(A11,'N2.for ref'!B$2:E$1266,3,0) -> MÊ TỬ
A12: 他人 | B12: たにん | C12: Người khác | D12: =VLOOKUP(A12,'N2.for ref'!B$2:E$1266,3,0) -> THA NHÂN
A13: 敵 | B13: てき | C13: Kẻ thù | D13: =VLOOKUP(A13,'N2.for ref'!B$2:E$1266,3,0) -> ĐỊCH
... A38: 全身 | B38: ぜんしん | C38: Toàn thân | D38: =VLOOKUP(A38,'N2.for ref'!B$2:E$1266,3,0) -> TOÀN THÂN
A39: しわ | B39: しわ | C39: Nếp nhăn
A40: 服装 | B40: ふくそう | C40: Quần áo, trang phục | D40: =VLOOKUP(A40,'N2.for ref'!B$2:E$1266,3,0) -> PHỤC TRANG
A41: 礼 | B41: れい | C41: lễ, cảm ơn | D41: LỄ
A42: 世辞 | B42: せじ | C42: Nịnh, ca tụng | D42: =VLOOKUP(A42,'N2.for ref'!B$2:E$1266,3,0) -> GIỚI TỪ
A43: 言い訳 | B43: いいわけ | C43: Giải thích, lý do lý trấu | D43: =VLOOKUP(A43,'N2.for ref'!B$2:E$1266,3,0) -> NGÔN DỊCH
A44: 話題 | B44: わだい | C44: Chủ đề | D44: =VLOOKUP(A44,'N2.for ref'!B$2:E$1266,3,0) -> THOẠI ĐỀ
A45: 秘密 | B45: ひみつ | C45: Bí mật | D45: =VLOOKUP(A45,'N2.for ref'!B$2:E$1266,3,0) -> BÍ MẬT
A46: 尊敬 | B46: そんけい | C46: Tôn trọng, tôn kính | D46: =VLOOKUP(A46,'N2.for ref'!B$2:E$1266,3,0) -> TÔN KÍNH
A47: 謙遜 | B47: けんそん | C47: Khiêm tốn | D47: =VLOOKUP(A47,'N2.for ref'!B$2:E$1266,3,0) -> KHIÊM TỐN
A48: 期待 | B48: きたい | C48: Mong chờ, mong đợi | D48: =VLOOKUP(A48,'N2.for ref'!B$2:E$1266,3,0) -> KÌ ĐÃI
A49: 苦労 | B49: くろう | C49: Lo lắng, vất vả | D49: =VLOOKUP(A49,'N2.for ref'!B$2:E$1266,3,0) -> KHỔ LAO
A50: 意志 | B50: いし | C50: ý chí | D50: Ý CHÍ
A51: 感情 | B51: かんじょう | C51: Biểu cảm, tâm trạng | D51: =VLOOKUP(A51,'N2.for ref'!B$2:E$1266,3,0) -> CẢM TÌNH
A52: 材料 | B52: ざいりょう | C52: Nguyên liệu (nấu ăn) | D52: =VLOOKUP(A52,'N2.for ref'!B$2:E$1266,3,0) -> TÀI LIỆU
A53: 石 | B53: いし | C53: Đá | D53: =VLOOKUP(A53,'N2.for ref'!B$2:E$1266,3,0) -> THẠCH
A54: 紐 | B54: ひも | C54: Sợi dây | D54: =VLOOKUP(A54,'N2.for ref'!B$2:E$1266,3,0) -> NỮU
A55: 券 | B55: けん | C55: Vé | D55: =VLOOKUP(A55,'N2.for ref'!B$2:E$1266,3,0) -> KHOÁN
A56: 名簿 | B56: めいぼ | C56: Danh bạ, danh sách | D56: =VLOOKUP(A56,'N2.for ref'!B$2:E$1266,3,0) -> DANH BỘ
A57: 表 | B57: ひょう | C57: Bảng biểu | D57: =VLOOKUP(A57,'N2.for ref'!B$2:E$1266,3,0) -> BIỂU
A58: 針 | B58: はり | C58: Cái kim | D58: =VLOOKUP(A58,'N2.for ref'!B$2:E$1266,3,0) -> CHÂM
A59: 栓 | B59: せん | C59: Cái nắp | D59: =VLOOKUP(A59,'N2.for ref'!B$2:E$1266,3,0) -> XUYÊN
A60: 湯気 | B60: ゆげ | C60: Hơi, khí | D60: =VLOOKUP(A60,'N2.for ref'!B$2:E$1266,3,0) -> THANG KHÍ
A61: 日当たり | B61: ひあたり | C61: nơi có ánh sáng chiếu vào | D61: NHẬT ĐƯƠNG
A62: 空 | B62: から | C62: Trống rỗng | D62: =VLOOKUP(A62,'N2.for ref'!B$2:E$1266,3,0) -> KHÔNG
A63: 斜め | B63: ななめ | C63: nghiêng | D63: =VLOOKUP(A63,'N2.for ref'!B$2:E$1266,3,0) -> TÀ
A64: = | B64: りれき | C64: lý lịch | D64: =VLOOKUP(A64,'N2.for ref'!B$2:E$1266,3,0) -> #N/A
A65: 娯楽 | B65: ごらく | C65: vui chơi, thú vui | D65: =VLOOKUP(A65,'N2.for ref'!B$2:E$1266,3,0) -> NGU LẠC
A66: 司会 | B66: しかい | C66: chủ trì buổi tiệc, hội nghị | D66: =VLOOKUP(A66,'N2.for ref'!B$2:E$1266,3,0) -> TY HỘI
A67: 歓迎 | B67: かんげい | C67: hoan nghênh | D67: =VLOOKUP(A67,'N2.for ref'!B$2:E$1266,3,0) -> HOAN NGHÊNH
A68: 窓口 | B68: まどぐち | C68: cửa bán vé | D68: =VLOOKUP(A68,'N2.for ref'!B$2:E$1266,3,0) -> SONG KHẨU
A69: 手続き | B69: てつづき | C69: thủ tục | D69: =VLOOKUP(A69,'N2.for ref'!B$2:E$1266,3,0) -> THỦ TỤC
A70: 徒歩 | B70: とほ | C70: đi bộ | D70: =VLOOKUP(A70,'N2.for ref'!B$2:E$1266,3,0) -> ĐỒ BỘ
A71: 駐車 | B71: ちゅうしゃ | C71: Đỗ xe | D71: =VLOOKUP(A71,'N2.for ref'!B$2:E$1266,3,0) -> CHÚ XA
A72: 違反 | B72: いはん | C72: vi phạm | D72: =VLOOKUP(A72,'N2.for ref'!B$2:E$1266,3,0) -> VI PHẢN
A73: 平日 | B73: へいじつ | C73: ngày thường | D73: =VLOOKUP(A73,'N2.for ref'!B$2:E$1266,3,0) -> BÌNH NHẬT
... A99: 募金 | B99: ぼきん | C99: quyên tiền, gây quỹ | D99: =VLOOKUP(A99,'N2.for ref'!B$2:E$1266,3,0) -> MỘ KIM
A100: 寄付 | B100: きふ | C100: đóng góp | D100: KÍ PHÓ
A101: 募集 | B101: ぼしゅう | C101: tuyển dụng | D101: =VLOOKUP(A101,'N2.for ref'!B$2:E$1266,3,0) -> MỘ TẬP
A102: 価値 | B102: かち | C102: giá trị | D102: =VLOOKUP(A102,'N2.for ref'!B$2:E$1266,3,0) -> GIÁ TRỊ
A103: 好む | B103: このむ | C103: thích | D103: =VLOOKUP(A103,'N2.for ref'!B$2:E$1266,3,0) -> HẢO
A104: 嫌う | B104: きらう | C104: ghét (mức độ 嫌う→恨む→憎む) | D104: =VLOOKUP(A104,'N2.for ref'!B$2:E$1266,3,0) -> HIỀM
A105: 願う | B105: ねがう | C105: ước, yêu cầu | D105: =VLOOKUP(A105,'N2.for ref'!B$2:E$1266,3,0) -> NGUYỆN
A106: 甘える | B106: あまえる | C106: nũng nịu | D106: =VLOOKUP(A106,'N2.for ref'!B$2:E$1266,3,0) -> CAM
A107: 甘やかす | B107: あまやかす | C107: nuông chiều (con cái) | D107: CAM
A108: 可愛がる | B108: かわいがる | C108: yêu mến, nâng niu | D108: =VLOOKUP(A108,'N2.for ref'!B$2:E$1266,3,0) -> KHẢ ÁI
A109: 気付く | B109: きづく | C109: nhận ra | D109: =VLOOKUP(A109,'N2.for ref'!B$2:E$1266,3,0) -> KHÍ PHÓ
A110: 疑う | B110: うたがう | C110: nghi ngờ | D110: =VLOOKUP(A110,'N2.for ref'!B$2:E$1266,3,0) -> NGHI
A111: 苦しむ | B111: くるしむ | C111: khổ, chịu đựng | D111: =VLOOKUP(A111,'N2.for ref'!B$2:E$1266,3,0) -> KHỔ
A112: 悲しむ | B112: かなしむ | C112: buồn | D112: =VLOOKUP(A112,'N2.for ref'!B$2:E$1266,3,0) -> BI
A113: がっかりする | B113: がっかりする | C113: thất vọng
A114: 励ます | B114: はげます | C114: động viên (慰める thiên về an ủi) | D114: =VLOOKUP(A114,'N2.for ref'!B$2:E$1266,3,0) -> LỆ
A115: 励む | B115: はげむ | C115: tự động viên mình | D115: LỆ
A116: 頷く | B116: うなずく | C116: gật đầu, đồng ý | D116: =VLOOKUP(A116,'N2.for ref'!B$2:E$1266,3,0) -> HẠM
A117: 張り切る | B117: はりきる | C117: hăm hở, làm việc chăm chỉ | D117: =VLOOKUP(A117,'N2.for ref'!B$2:E$1266,3,0) -> TRƯƠNG
A118: 威張る | B118: いばる | C118: kiêu ngạo | D118: =VLOOKUP(A118,'N2.for ref'!B$2:E$1266,3,0) -> UY TRƯƠNG
A119: 怒鳴る | B119: どなる | C119: hét lên | D119: =VLOOKUP(A119,'N2.for ref'!B$2:E$1266,3,0) -> NỘ MINH
A120: 暴れる | B120: あばれる | C120: nổi giận, bạo lực | D120: =VLOOKUP(A120,'N2.for ref'!B$2:E$1266,3,0) -> BẠO
A121: しゃがむ | B121: しゃがむ | C121: ngồi chơi, ngồi xổm
A122: 退く | B122: どく | C122: làm tránh ra | D122: =VLOOKUP(A122,'N2.for ref'!B$2:E$1266,3,0) -> THOÁI
A123: 退ける | B123: どける | C123: tránh ra | D123: =VLOOKUP(A123,'N2.for ref'!B$2:E$1266,3,0) -> THOÁI
A124: 被る | B124: かぶる | C124: đội (hướng về bản thân) | D124: =VLOOKUP(A124,'N2.for ref'!B$2:E$1266,3,0) -> BỊ
A125: 被せる | B125: かぶせる | C125: phủ lên (hướng về phía khác) | D125: =VLOOKUP(A125,'N2.for ref'!B$2:E$1266,3,0) -> BỊ
A126: 齧る | B126: かじる | C126: nhai, cắn (dấu vết) | D126: =VLOOKUP(A126,'N2.for ref'!B$2:E$1266,3,0) -> NIẾT
A127: 撃つ | B127: うつ | C127: bắn | D127: =VLOOKUP(A127,'N2.for ref'!B$2:E$1266,3,0) -> KÍCH
A128: 漕ぐ | B128: こぐ | C128: đạp xe, chèo | D128: =VLOOKUP(A128,'N2.for ref'!B$2:E$1266,3,0) -> TÀO
A129: 敷く | B129: しく | C129: trải ra | D129: =VLOOKUP(A129,'N2.for ref'!B$2:E$1266,3,0) -> PHU
A130: 注ぐ | B130: つぐ | C130: rót (rượu) | D130: =VLOOKUP(A130,'N2.for ref'!B$2:E$1266,3,0) -> CHÚ
A131: 配る | B131: くばる | C131: phân phát | D131: =VLOOKUP(A131,'N2.for ref'!B$2:E$1266,3,0) -> PHỐI
A132: 放る | B132: ほうる | C132: ném, bỏ mặc | D132: =VLOOKUP(A132,'N2.for ref'!B$2:E$1266,3,0) -> PHÓNG
A133: 掘る | B133: ほる | C133: đào, khai quật | D133: =VLOOKUP(A133,'N2.for ref'!B$2:E$1266,3,0) -> QUẬT
A134: 撒く | B134: まく | C134: rắc, rải | D134: =VLOOKUP(A134,'N2.for ref'!B$2:E$1266,3,0) -> TÁT
A135: 測る・計る・量る | B135: はかる | C135: đo, đo đạc
A136: 占う | B136: うらなう | C136: dự đoán, bói | D136: =VLOOKUP(A136,'N2.for ref'!B$2:E$1266,3,0) -> CHIẾM
A137: 引っ張る | B137: ひっぱる | C137: kéo | D137: =VLOOKUP(A137,'N2.for ref'!B$2:E$1266,3,0) -> DẪN TRƯƠNG
A138: 突く | B138: つく | C138: chọc, đâm | D138: =VLOOKUP(A138,'N2.for ref'!B$2:E$1266,3,0) -> ĐỘT
A139: 突き当たる | B139: つきあたる | C139: đi hết đường, đến cuối đường | D139: =VLOOKUP(A139,'N2.for ref'!B$2:E$1266,3,0) -> ĐỘT ĐƯƠNG
A140: 立ち止まる | B140: たちどまる | C140: dừng lại | D140: =VLOOKUP(A140,'N2.for ref'!B$2:E$1266,3,0) -> LẬP CHỈ
A141: 近寄る | B141: ちかよる | C141: tiếp cận | D141: =VLOOKUP(A141,'N2.for ref'!B$2:E$1266,3,0) -> CẬN KÍ
A142: 横切る | B142: よこぎる | C142: băng xéo qua, cắt ngang (hàng, người khác) | D142: =VLOOKUP(A142,'N2.for ref'!B$2:E$1266,3,0) -> HOÀNH THIẾT
A143: 転ぶ | B143: ころぶ | C143: ngã | D143: =VLOOKUP(A143,'N2.for ref'!B$2:E$1266,3,0) -> CHUYỂN
A144: 躓く | B144: つまずく | C144: vấp (Vd: vấp hòn đá) | D144: =VLOOKUP(A144,'N2.for ref'!B$2:E$1266,3,0) -> CHÍ
A145: ひく | B145: ひく | C145: chèn, cán qua (車にひかれる bị xe cán)
A146: 溺れる | B146: おぼれる | C146: chìm, đắm | D146: =VLOOKUP(A146,'N2.for ref'!B$2:E$1266,3,0) -> NỊCH
A147: 痛む | B147: いたむ | C147: đau | D147: =VLOOKUP(A147,'N2.for ref'!B$2:E$1266,3,0) -> THỐNG
A148: かかる | B148: かかる | C148: bị nhiễm
A149: 酔う | B149: よう | C149: say | D149: =VLOOKUP(A149,'N2.for ref'!B$2:E$1266,3,0) -> TỬU
...

Sheet ngữ pháp n2
A1: 完全マスター 日本語能力試験 ２級 文法 阮登貴
A6: 完全マスター
A7: 日本語能力試験２級
A8: 文法
A13: 編集・翻訳 阮登貴 武氏河宣
A14: 神戸・河内 ２００８
A15: 1
A19: Chia sẻ tài liệu : Chiasemoi.com
A20: _x000C_完全マスター 日本語能力試験 ２級 文法 阮登貴
A25: 目次
A26: １ ～として（は）／～としても／～としての ............................................................................................. 7
A27: ２ ～とともに..................................................................................................................................................... 7
A28: ３ ～において（は）／～においても／～における ..................................................................................... 8
A29: ４ ～に応じて／～に応じ／～に応じた ......................................................................................................... 8
A30: ５ ～にかわって／～にかわり ......................................................................................................................... 8
A31: ６ ～に比べて／～に比べ ................................................................................................................................. 9
A32: ７ ～にしたがって／～にしたがい 従い／したがい ............................................................................. 9
A33: ８ ～につれて／～につれ ................................................................................................................................. 9
A34: ９ ～に対して（は）／～に対し／～に対しても／～に対する ............................................................... 10
... A63: ３６ ～一方だ................................................................................................................................................... 22
A64: 2
A65: _x000C_完全マスター 日本語能力試験 ２級 文法 阮登貴
A67: ３７ ～おそれがある ....................................................................................................................................... 22
A68: ３８ ～ことになっている ............................................................................................................................... 22
A69: ３９ ～ことはない........................................................................................................................................... 23
A70: ４０ ～しかない............................................................................................................................................... 23
A71: ４１ ～ということだ ....................................................................................................................................... 23
A72: ４２ ～まい／～まいか ................................................................................................................................... 24
A73: ４３ ～わけがない／～わけはない ............................................................................................................... 24
A74: ４４ ～わけにはいかない／～わけにもいかない ....................................................................................... 25
A75: ４５ ～から～にかけて ................................................................................................................................... 25
A76: ４６ たとえ～ても／たとえ～でも ............................................................................................................... 26
A77: ４７ ～さえ～ば............................................................................................................................................... 26
... A107: ７５ ～あまり................................................................................................................................................... 36
A108: 3
A109: _x000C_完全マスター 日本語能力試験 ２級 文法 阮登貴
A111: ７６ ～一方／～一方で（は） ....................................................................................................................... 36
A112: ７７ ～上で（は）／～上の／～上でも／～上での ................................................................................... 37
A113: ７８ ～限り（は）／～かぎりでは／～ないかぎり（は） ....................................................................... 37
A114: ７９ ～（か）と思うと／～（か）と思ったら ........................................................................................... 39
A115: ８０ ～か～ないかのうちに ........................................................................................................................... 39
A116: ８１ ～からいうと／～からいえば／～からいって ................................................................................... 39
A117: ８２ ～からといって ....................................................................................................................................... 39
A118: ８３ ～から見ると／～から見れば／～から見て（も） ........................................................................... 40
A119: ８４ ～きり（だ）........................................................................................................................................... 40
A120: ８５ ～くせに................................................................................................................................................... 41
A121: ８６ ～ことから............................................................................................................................................... 41
... A150: １１５ ～どころではない／～どころではなく ........................................................................................... 52
A151: 4
A152: _x000C_完全マスター 日本語能力試験 ２級 文法 阮登貴
A154: １１６ ～からして........................................................................................................................................... 52
A155: １１７ ～からすると／～からすれば ........................................................................................................... 53
A156: １１８ ～からには／～からは ....................................................................................................................... 53
A157: １１９ ～ことだから ....................................................................................................................................... 53
A158: １２０ ～だけ／～だけあって／～だけに／～だけの ............................................................................... 54
A159: １２１ ～にあたって／～に当たり ............................................................................................................... 55
A160: １２２ ～にかけては／～にかけても ........................................................................................................... 55
A161: １２３ ～に際して／～に際し／～に際しての ........................................................................................... 55
A162: １２４ ～に先立って／～に先立ち／～に先立つ ....................................................................................... 56
A163: １２５ ～にしたら／～にすれば／～にしても ........................................................................................... 56
A164: １２６ ～につき............................................................................................................................................... 56
... A193: １５５ ～（よ）うではないか／～（よ）うじゃないか ........................................................................... 68
A194: 5
A195: _x000C_完全マスター 日本語能力試験 ２級 文法 阮登貴
A197: １５６ ～得る／～得ない ............................................................................................................................... 68
A198: １５７ ～かねない........................................................................................................................................... 69
A199: １５８ ～かねる............................................................................................................................................... 69
A200: １５９ ～ことか............................................................................................................................................... 69
A201: １６０ ～ことだ............................................................................................................................................... 69
A202: １６１ ～ざるを得ない ................................................................................................................................... 70
A203: １６２ ～次第だ／～次第で（は） ............................................................................................................... 70
A204: １６３ ～っこない........................................................................................................................................... 71
A205: １６４ ～というものだ ................................................................................................................................... 71
A206: １６５ ～というものではない／～というものでもない ........................................................................... 71
A207: １６６ ～ないことはない／～ないこともない ........................................................................................... 72
... A214: １７３ ～ようがない／～ようもない ........................................................................................................... 75
A219: 6
A220: _x000C_完全マスター 日本語能力試験 ２級 文法 阮登貴
A224: １ ～として（は）／～としても／～としての
A225: 意味 ＜立場、資格、種類をはっきり言う。＞
A226: Nói về lập trường, tư cách, chủng loại
A227: 接続 [名]＋として
A228: ① 彼は国費留学生として日本へ来た。
A229: Anh ấy đã đến Nhật với tư cách là lưu học sinh ngân sách nhà nước
A230: ② この病気は難病として認定された。
A231: Căn bệnh này được nhận định là một bệnh nan y.
A232: ③ 彼は医者であるが、小説家としても有名である。
A233: Tuy ông ấy là một bác sĩ, nhưng cũng nổi tiếng với tư cách là một tiểu thuyết gia.
A234: ④ あの人は学者としては立派だが、人間としては尊敬できない。
... A262: Giáo dục phổ cập vừa là nghĩa vụ, còn là quyền lợi của nhân dân.
A267: 7
A268: _x000C_完全マスター 日本語能力試験 ２級 文法 阮登貴
A270: C 意味 一つの変化と一緒に、別の変化が起こる。
A271: Cùng với một sự thay đổi, một sự thay đổi khác diễn ra.
A272: 接続 [動-辞書形]
A273: [名] ＋とともに
A274: おとろ
A275: ① 年をとるとともに、体力が 衰 える。
A276: Cùng với tuổi cao, thể lực cũng yếu đi.
A277: ② 自動車が普及するとともに、交通事故も増えてきた。
...

Sheet N1
A2: 1 | B2: 青春 | C2: せいしゅん | D2: thanh xuân
B3: 青春時代 | C3: せいしゅんじだい | D3: tuổi thanh xuân, tuổi trẻ
A4: 2 | B4: 晩年 | C4: ばんねん | D4: cuối đời, tuổi xế bóng
B5: 最晩年 | C5: さいばんねん | D5: những năm cuối đời
A6: 3 | B6: 葬式 | C6: そうしき | D6: tang lễ, đám tang
A7: 4 | B7: 世帯 | C7: せたい | D7: hộ gia đình
B8: 世帯主 | C8: せたいぬし | D8: chủ hộ
B9: 世帯数 | C9: せたいすう | D9: số lượng hộ gia đình
B10: 二世帯 | C10: にせたい | D10: 2 hộ gia đình
A11: 5 | B11: 世間 | C11: せけん | D11: thế gian, xã hội
B12: 世の中 | C12: よのなか | D12: xã hội
B13: 世間体 | C13: せけんてい | D13: miệng lưỡi thế gian
A14: 6 | B14: 庶民 | C14: しょみん | D14: dân đen, dân thường
B15: 庶民的 | C15: しょみんてき | D15: thông thường, tự nhiên, bình thường, mang tính phổ thông
B16: 庶民階級 | C16: しょみんかいきゅう | D16: giai cấp nhân dân
A17: 7 | B17: おんぶする | D17: ①địu, cõng trên lưng ②phụ thuộc, sống nhờ (実家に)
B18: 抱っこする | C18: だっこする | D18: ôm,ẵm trên tay
A19: 8 | B19: 片言 | C19: かたこと | D19: ① nói bập bõm, nói đứt đoạn, nói không trôi chảy ② tám chuyện
A20: 9 | B20: 夜更かし | C20: よふかし | D20: thức khuya
B21: 夜更かし（を）する | D21: thức khuya
B22: 夜更け | C22: よふけ | D22: Đêm khuya
A23: 10 | B23: 家出 | C23: いえで | D23: ① bỏ nhà ra đi ② đi ra khỏi nhà
B24: 家出する | D24: bỏ nhà ra đi
A25: 11 | B25: 戸締り(を)する | C25: とじまり | D25: khóa cửa
A26: 12 | B26: ずぶ濡れ | C26: ずぶぬれ | D26: ướt sũng
A27: 13 | B27: 顔つき | C27: かおつき | D27: vẻ mặt, nét mặt
A28: 14 | B28: 身なり | C28: みなり | D28: diện mạo
B29: 身なりをする | D29: thể hiện diện mạo
B30: 身なりがいい⇔悪い | D30: diện mạo tốt ⇔ xấu
A31: 15 | B31: 身の回り | C31: みのまわり | D31: những thứ xung quanh bản thân
B32: 身の回りのこと | D32: những việc thường ngày
A33: 16 | B33: 身振り | C33: みぶり | D33: Điệu bộ, cử chỉ
A34: 17 | B34: 良心 | C34: りょうしん | D34: lương tâm
B35: 良心がある⇔ない | D35: có lương tâm ⇔ không có lương tâm
B36: 良心が痛む | D36: đau đớn lương tâm
B37: 良心が恥じる | C37: はじる | D37: lương tâm xấu hổ
B38: 良心の呵責 | C38: かしゃく | D38: sự cắn rứt lương tâm
A39: 18 | B39: 素質 | C39: そしつ | D39: tố chất, năng khiếu （素質+努力＝才能）
A40: 19 | B40: 好意 | C40: こうい | D40: hảo ý, lòng tốt
B41: 敵意 | C41: てきい | D41: sự thù địch
A42: 20 | B42: ため息 | C42: ためいき | D42: tiếng thở dài
B43: ため息をつく | D43: thở dài
A44: 21 | B44: ど忘れ | C44: どわすれ | D44: sự đãng trí
B45: ど忘れする | D45: đãng trí
A46: 22 | B46: 用心 | C46: ようじん | D46: cẩn thận đối với nguy hiểm (cẩn thận khi đi trên đường vắng ban đêm)
A47: 23 | B47: 予感する | C47: よかん | D47: dự cảm, linh tính
B48: 予感がある | D48: có cảm giác (thuộc về kinh nghiệm) VD: đã có cảm giác sẽ thất bại.
B49: 予感がする | D49: có cảm giác (hành động) VD: trong lúc thực hiện dự án này tôi đã cảm thấy không khả thi.
A50: 24 | B50: 視線 | C50: しせん | D50: ánh mắt, ánh nhìn
B51: 視線が合う | D51: nhìn nhau
B52: 視線を合わせる | D52: bị nhìn nên nhìn lại, hãy nhìn nhau đi, hay làm lành (giận nhau)
B53: 視線を逸らす | C53: しせんをそらす | D53: trốn tránh ánh mắt của người khác
B54: 視線を外す | C54: はずす | D54: rời mắt, không nhìn nữa
B55: 視線を浴びる | D55: bị nhìn, bị để ý
A56: 25 | B56: 迷信 | C56: めいしん | D56: mê tín
B57: 迷信を信じる | D57: tin vào điều mê tín
A58: 26 | B58: 縁 | C58: えん | D58: duyên nợ
B59: 血縁 | C59: けつえん | D59: cùng dòng máu, cùng huyết thống
B60: 縁故 | C60: えんこ | D60: duyên cớ (có duyên nợ mới kết hôn, có duyên mới trở thành anh em , v.v)
B61: 離縁 | C61: りえん | D61: cắt đứt duyên nợ (ly dị,v.v)
B62: 絶縁 | C62: ぜつえん | D62: ①cắt đứt duyên nợ、② cách điện、cách nhiệt
B63: 縁起 | C63: えんぎ | D63: Điềm báo
A64: 27 | B64: 使い捨て | C64: つかいすて | D64: sử dụng 1 lần rồi bỏ
A65: 28 | B65: 下取り | C65: したどり | D65: đổi cũ lấy mới, có bù thêm tiền
B66: 下取りに出す | D66: đưa món đồ cũ ra mua đổi món đồ mới
A67: 29 | B67: 倹約 | C67: けんやく | D67: tiết kiệm (không dùng với tài nguyên thiên nhiên, thời gian)
A68: 30 | B68: 出費する | C68: しゅっぴ | D68: chi tiêu、nói về mức độ (が多い、が少ない、がかさむ tăng, を切り詰める cắt giảm)
B69: 支出する | C69: ししゅつ | D69: đi với số tiền, khoản tiền chứa đựng ý nghĩa bao nhiêu tiền(予算, 5000円)
A70: 31 | B70: 会計 | C70: かいけい | D70: kế toán, tính tiền
B71: 会計係 | C71: かいけいがかり | D71: nhân viên kế toán
B72: 会計士 | C72: かいけいし | D72: nhân viên kế toán
A73: 32 | B73: 所得 | C73: しょとく | D73: sau khi đã khấu trừ, thường dùng trong sổ sách, giấy tờ, tính chính xác
B74: 所得税 | C74: しょとくぜい | D74: thuế thu nhập
B75: 収入 | C75: しゅうにゅう | D75: thu nhập chung, tổng thu về chưa trừ chi phí(đối với cửa hàng =売り上げ )
A76: 33 | B76: 採用する | C76: さいよう | D76: ①thuê, mướn, tuyển dụng ②sử dụng, thừa nhận
A77: 34 | B77: 雇用する | C77: こよう | D77: thuê, mướn, tuyển dụng (từ này chỉ dùng cho con người )
A78: 35 | B78: 所属する | C78: しょぞく | D78: thường nói về tổ chức của con người, nhìn thấy được （営業部に、区のボランティア会に）
B79: 所属部隊 | C79: しょぞくぶたい | D79: thuộc về quân đội
B80: 属する | C80: ぞくする | D80: thường nói về lĩnh vực, những thứ không nhìn thấy được
A81: 36 | B81: 待遇 | C81: たいぐう | D81: ①chế độ đãi ngộ ②tiếp đón (không dùng với đãi món ăn, dùng 接待)
A82: 37 | B82: 派遣する | C82: はけん | D82: sự sai bảo, sự phái đi chủ thể của hành động là bản thân → 派遣される chủ thể của hành động không phải là bản thân → 派遣する
B83: 人材派遣 | C83: じんざいはけん | D83: nhân viên hợp đồng (khác với nhân viên chính thức)
A84: 38 | B84: 赴任する | C84: ふにん | D84: chuyển công tác (những người có trách nhiệm, vai trò cao như tổ trưởng, trưởng phòng,... nhận nhiệm vụ xây dựng một chi nhanh mới hoặc một trách nhiệm mới cao hơn, khó khăn hơn) chủ thể của hành động là bản thân → 赴任する hoặc 赴任させられる
B85: 転勤する | D85: chuyển công tác, chuyển đến chi nhánh khác thuộc cùng công ty
A86: 39 | B86: 地元 | C86: じもと | D86: địa phương của mình, quê nhà
A87: 40 | B87: 現役 | C87: げんえき | D87: đang hoạt động, đang đảm nhiệm
A88: 41 | B88: 指図する | C88: さしず | D88: chỉ thị, hướng dẫn .
A89: 42 | B89: 操縦する | C89: そうじゅう | D89: ①điều khiển, vận hành (máy bay, tàu thuyền) ②điều khiển con người
B90: 操る | C90: あやつる | D90: điều khiển dùng chung cho cả nghĩa đen và nghĩa bóng(馬、政権、人、機械)
A91: 43 | B91: 主食 | C91: しゅしょく | D91: lương thực chính, thức ăn chính trong bữa ăn (gạo, cơm, v.v)
B92: 副食 | C92: ふくしょく | D92: đồ ăn, món ăn (không phải cơm)
A93: 44 | B93: 食物 | C93: しょくもつ | D93: thực phẩm
A94: 45 | B94: 穀物 | C94: こくもつ | D94: ngũ cốc, bột mì, đậu,v.v ngoại trừ gạo
A95: 46 | B95: 豊作 | C95: ほうさく | D95: trúng mùa, mùa màng bội thu
B96: 凶作 | C96: きょうさく | D96: Sự mất mùa
B97: 不作 | C97: ふさく | D97: Sự mất mùa
A98: 47 | B98: 例年 | C98: れいねん | D98: định kì hàng năm
B99: 例年にない+N | D99: N mà định kì mọi năm không có
A100: 48 | B100: 種 | C100: たね | D100: ①hạt, hạt giống
B101: 話の種 | D101: ②cốt lõi, trọng tâm (vấn đề, câu chuyện)
...

Sheet ngữ pháp n1
A16: 日本語能力試験一級文法 阮登貴
A21: 日本語能力試験一級
A22: 文法
A27: 編集・翻訳 阮登貴 武氏河宣
A28: 神戸・河内 ２００８
A29: ©dangquybk@gmail.com
A30: (Powered by jlpt.info, copyright reserved 2007)
A35: 1
A36: _x000C_日本語能力試験一級文法 阮登貴
A40: 目次
A41: 1. A あっての B......................................................................................................................................... 5
A42: 2. A いかんで/では/によっては B、B は A いかんだ A のいかんによらず/かかわらず B............ 5
A43: 3. A う(意向形)が/と B A う(意向形)が A まいが/A う(意向形)と A まいと B................................. 5
A44: 4. A う(意向形)にも A(可能形)ない ....................................................................................................... 6
A45: 5. A 限りだ ................................................................................................................................................ 7
A46: 6. A(た)が最後 B ....................................................................................................................................... 7
A47: 7. A かたがた B......................................................................................................................................... 7
A48: 8. A かたわら B......................................................................................................................................... 8
A49: 9. A がてら B............................................................................................................................................. 8
A50: 10. A が早いか B......................................................................................................................................... 9
... A77: 37. A といい B といい.............................................................................................................................. 20
A78: 2
A79: _x000C_日本語能力試験一級文法 阮登貴
A80: 38. A というところだ/といったところだ ............................................................................................. 20
A81: 39. A といえども B................................................................................................................................... 21
A82: 40. A といったらない/といったらありはしない(ありゃしない)....................................................... 21
A83: 41. A と思いきや B................................................................................................................................... 21
A84: 42. A ときたら B....................................................................................................................................... 22
A85: 43. A ところを B....................................................................................................................................... 22
A86: 44. A としたところで/としたって/にしたところで/にしたって B.................................................... 23
A87: 45. A とは .................................................................................................................................................. 23
A88: 46. A とはいえ B....................................................................................................................................... 23
A89: 47. A とばかりに B................................................................................................................................... 24
A90: 48. A ともなく/ともなしに(していると/していたら).......................................................................... 24
... A119: 77. A ばそれまでだ .................................................................................................................................. 36
A120: 3
A121: _x000C_日本語能力試験一級文法 阮登貴
A122: 78. ひとり A だけでなく/ひとり A のみならず.................................................................................... 36
A123: 79. A べからず/べからざる ..................................................................................................................... 37
A124: 80. A べく .................................................................................................................................................. 37
A125: 81. A にあるまじき .................................................................................................................................. 38
A126: 82. A までだ/までのことだ ..................................................................................................................... 38
A127: 83. A までもない/までもなく ................................................................................................................. 38
A128: 84. A まみれ .............................................................................................................................................. 39
A129: 85. A めく .................................................................................................................................................. 39
A130: 86. A もさることながら B....................................................................................................................... 40
A131: 87. A ものを B........................................................................................................................................... 40
A132: 88. A や/や否や B...................................................................................................................................... 40
... A143: 99. A んばかりだ/んばかりに/んばかりの ............................................................................................ 45
A148: 4
A149: _x000C_日本語能力試験一級文法 阮登貴
A150: 1. A あっての B
A151: 意味 A があるからこそ B がある。A がなければ B もない。
A152: Chính vì có A nên mới có B. Nếu không có A thì cũng chẳng có B.
A153: 用例
A154: ① どんなに有名でも、お客様あってのお店です。
A155: Cho dù nổi tiếng đến mấy, có khách hàng mới có nhà hàng.
A156: ② あなたあっての私です。
A157: Chính vì có em nên mới có anh./Anh không thể sống thiếu em.
A158: ③ 私が今日こうして活躍できるのも先輩のご支援あってのことです。
A159: Những hoạt động của tôi được đến chừng này chính là nhờ sự hỗ trợ của các senpai.
A160: ④ 今の安定した生活も若いときの苦労あってのものです。
... A191: Cho dù A, hay không A, B.
A192: 5
A193: _x000C_日本語能力試験一級文法 阮登貴
A194: 用例
A195: ① 彼が困ろうが、私には関係がない。
A196: Dù anh ta khốn khổ thế nào, tôi chẳng liên quan gì.
A197: ② 他人がどんなに迷惑しようと自分には関係ないというのはあまりにも身勝手だ。
A198: Nói là người khác có làm phiền đến mấy cũng không liên quan đến mình thật là ích kỷ.
A199: ③ 親が反対しようとしまいと、私は彼と結婚します。
A200: Dù bố mẹ có phản đối hay không, tôi vẫn sẽ lấy anh ấy.
A201: ④ 彼が来ようが来まいが、時間になったら出発します。
A202: Anh ta có đến hay không cũng thế, đến giờ là xuất phát.
A203: ⑤ レコードが売れようが売れるまいが関係なく彼は自分の作りたい音楽を作り続けた。
A204: Không quan tâm là đĩa có bán được hay không, anh ta vẫn tiếp tục làm các đĩa nhạc mà mình thích.
... A233: ×ビルの 2 階からは、階段がなければ、落ちようにも落ちられない。
A238: 6
A239: _x000C_日本語能力試験一級文法 阮登貴
A240: 5. A 限りだ
A241: 意味 最高に A だ。A là tối đa, cao nhất.
A242: 用例
A243: ① こんなに盛大な結婚式を挙げることができて、うれしい限りです。
A244: Tổ chức được lễ cưới hoành tráng thế này, còn gì vui sướng bằng. (tiệc cưới: 結婚披露宴)
A245: ② たったひとりの肉親だった姉を亡くして、さびしい限りです。
A246: Mất đi chị gái ruột duy nhất, thật không gì đau đớn thế.
A247: ③ 言葉がわからない外国で暮らすのだと思うと、心細い限りでした。
A248: Nghĩ đến sống ở nước ngoài mà không biết tiếng, thật là đơn độc.
A251: 6. A(た)が最後 B
A252: 意味 もし A したら、B という結果になり、もう止められない。
... A283: Tiện thể đi mời cưới, tôi đã đến thăm thầy giáo..
A284: 7
A285: _x000C_日本語能力試験一級文法 阮登貴
A286: 注意
A287: *2 級－63「A ついでに B」、1 級－9「A がてら B」と類似。
A288: Giống ngữ pháp 2 kyu “A ついでに B”,1 kyuu “A がてら B”
A291: 8. A かたわら B
A292: 意味 A と同時に/の合間に B をする。Trong khi làm A, làm B.
A293: 用例
A294: ① 彼は勉学のかたわら、アルバイトをしている。
...

Sheet N2.for ref
A1: STT | B1: 漢字 | C1: ひらがな | D1: Hán Việt | E1: Nghĩa | F1: Bổ sung
A2: 1 | B2: 人生 | C2: じんせい | D2: NHÂN SINH | E2: Cuộc sống | F2: =+VLOOKUP(B2,'N2'!$A$2:$D$1287,1,0) -> 人生
A3: 2 | B3: 一生 | C3: いっせい | D3: NHẤT SINH | E3: Một đời | F3: =+VLOOKUP(B3,'N2'!$A$2:$D$1287,1,0) -> #N/A | I3: どだい
A4: 3 | B4: 生涯 | C4: しょうがい | D4: SINH NHAI | E4: Sinh nhai, sự nghiệp | F4: =+VLOOKUP(B4,'N2'!$A$2:$D$1287,1,0) -> #N/A
A5: 4 | B5: 人間 | C5: にんげん | D5: NHÂN GIAN | E5: Nhân gian | F5: =+VLOOKUP(B5,'N2'!$A$2:$D$1287,1,0) -> 人間
A6: 5 | B6: 人物 | C6: じんぶつ | D6: NHÂN VẬT | E6: Nhân vật (con người) | F6: =+VLOOKUP(B6,'N2'!$A$2:$D$1287,1,0) -> 人物
A7: 6 | B7: 平等 | C7: へいとう | D7: BÌNH ĐẲNG | E7: Bình đẳng | F7: =+VLOOKUP(B7,'N2'!$A$2:$D$1287,1,0) -> #N/A
A8: 7 | B8: 人 | C8: ひと | D8: NHÂN | E8: Người | F8: =+VLOOKUP(B8,'N2'!$A$2:$D$1287,1,0) -> 人
A9: 8 | B9: 人類 | C9: じんるい | D9: NHÂN LOẠI | E9: Nhân loại | F9: =+VLOOKUP(B9,'N2'!$A$2:$D$1287,1,0) -> #N/A
A10: 9 | B10: 祖先 | C10: そせん | D10: TỔ TIÊN | E10: Tổ tiên | F10: =+VLOOKUP(B10,'N2'!$A$2:$D$1287,1,0) -> 祖先
A11: 10 | B11: 発生 | C11: はっせい | D11: PHÁT SINH | E11: Phát sinh | F11: =+VLOOKUP(B11,'N2'!$A$2:$D$1287,1,0) -> 発生
A12: 11 | B12: 親戚 | C12: しんせき | D12: THÂN THÍCH | E12: Họ hàng | F12: =+VLOOKUP(B12,'N2'!$A$2:$D$1287,1,0) -> 親戚
A13: 12 | B13: 親類 | C13: しんるい | D13: THÂN LOẠI | E13: Họ hàng | F13: =+VLOOKUP(B13,'N2'!$A$2:$D$1287,1,0) -> #N/A
A14: 13 | B14: 親族 | C14: しんぞく | D14: THÂN TỘC | E14: Họ hàng | F14: =+VLOOKUP(B14,'N2'!$A$2:$D$1287,1,0) -> #N/A
A15: 14 | B15: 夫婦 | C15: ふうふ | D15: PHU PHỤ | E15: Vợ chồng | F15: =+VLOOKUP(B15,'N2'!$A$2:$D$1287,1,0) -> 夫婦
... A83: 82 | B83: 玄関 | C83: げんかん | D83: HUYỀN QUAN | E83: Cửa ra vào | F83: =+VLOOKUP(B83,'N2'!$A$2:$D$1287,1,0) -> #N/A
A84: 83 | B84: しわ | C84: しわ | E84: Nếp Nhăn | F84: =+VLOOKUP(B84,'N2'!$A$2:$D$1287,1,0) -> #N/A
A85: 84 | B85: お年を取る | C85: おとしをとる | D85: NIÊN THỦ | E85: Về già, tuổi già | F85: =+VLOOKUP(B85,'N2'!$A$2:$D$1287,1,0) -> #N/A
A86: 85 | B86: 服装 | C86: ふくそう | D86: PHỤC TRANG | E86: Quần áo, trang phục | F86: =+VLOOKUP(B86,'N2'!$A$2:$D$1287,1,0) -> 服装
A87: 86 | B87: 面接 | C87: めんせつ | D87: DIỆN TIẾP | E87: Phỏng vấn | F87: =+VLOOKUP(B87,'N2'!$A$2:$D$1287,1,0) -> #N/A
A88: 87 | B88: お礼 | C88: おれい | D88: LỄ | E88: Lễ, cảm ơn | F88: =+VLOOKUP(B88,'N2'!$A$2:$D$1287,1,0) -> #N/A
A89: 88 | B89: お辞儀 | C89: おじぎ | D89: TỪ NGHI | E89: Cúi chào | F89: =+VLOOKUP(B89,'N2'!$A$2:$D$1287,1,0) -> #N/A
A90: 89 | B90: 述べる | C90: のべる | D90: THUẬT | E90: Phát biểu, thuật lại | F90: =+VLOOKUP(B90,'N2'!$A$2:$D$1287,1,0) -> 述べる
A91: 90 | B91: 世辞 | C91: せじ | D91: GIỚI TỪ | E91: Nịnh, ca tụng | F91: =+VLOOKUP(B91,'N2'!$A$2:$D$1287,1,0) -> 世辞
A92: 91 | B92: 言い訳 | C92: いいわけ | D92: NGÔN DỊCH | E92: Giải thích, lý do lý trấu | F92: =+VLOOKUP(B92,'N2'!$A$2:$D$1287,1,0) -> 言い訳
A93: 92 | B93: 認め | C93: みとめ | D93: XÁC | E93: Thừa nhận | F93: =+VLOOKUP(B93,'N2'!$A$2:$D$1287,1,0) -> #N/A
A94: 93 | B94: 話題 | C94: わだい | D94: THOẠI ĐỀ | E94: Chủ đề | F94: =+VLOOKUP(B94,'N2'!$A$2:$D$1287,1,0) -> 話題
A95: 94 | B95: 豊富 | C95: ほうふ | D95: PHONG PHÚ | E95: Phong phú | F95: =+VLOOKUP(B95,'N2'!$A$2:$D$1287,1,0) -> #N/A
A96: 95 | B96: 秘密 | C96: ひみつ | D96: BÍ MẬT | E96: Bí mật | F96: =+VLOOKUP(B96,'N2'!$A$2:$D$1287,1,0) -> 秘密
... A211: 210 | B211: 泣く | C211: なく | D211: KHẤP | E211: Khóc | F211: =+VLOOKUP(B211,'N2'!$A$2:$D$1287,1,0) -> #N/A
A212: 211 | B212: がっかりする | C212: がっかりする | E212: Thất vọng | F212: =+VLOOKUP(B212,'N2'!$A$2:$D$1287,1,0) -> がっかりする
A213: 212 | B213: 励ます | C213: はげます | D213: LỆ | E213: Động viên | F213: =+VLOOKUP(B213,'N2'!$A$2:$D$1287,1,0) -> 励ます
A214: 213 | B214: 頷く | C214: うなずく | D214: HẠM | E214: Gật đầu | F214: =+VLOOKUP(B214,'N2'!$A$2:$D$1287,1,0) -> 頷く
A215: 214 | B215: 張り切る | C215: はりきる | D215: TRƯƠNG | E215: Hăm hở, chăm chỉ làm việc | F215: =+VLOOKUP(B215,'N2'!$A$2:$D$1287,1,0) -> 張り切る
A216: 215 | B216: 威張る | C216: いばる | D216: UY TRƯƠNG | E216: Kiêu ngạo | F216: =+VLOOKUP(B216,'N2'!$A$2:$D$1287,1,0) -> 威張る
A217: 216 | B217: 怒鳴る | C217: どなる | D217: NỘ MINH | E217: Hét lên, gào lên | F217: =+VLOOKUP(B217,'N2'!$A$2:$D$1287,1,0) -> 怒鳴る
A218: 217 | B218: 暴れる | C218: あばれる | D218: BẠO | E218: Bạo lực, nổi giận | F218: =+VLOOKUP(B218,'N2'!$A$2:$D$1287,1,0) -> 暴れる
A219: 218 | B219: しゃがむ | C219: しゃがむ | E219: Ngồi chơi, ngồi xổm | F219: =+VLOOKUP(B219,'N2'!$A$2:$D$1287,1,0) -> しゃがむ
A220: 219 | B220: 退く | C220: どく | D220: THOÁI | E220: Tránh ra | F220: =+VLOOKUP(B220,'N2'!$A$2:$D$1287,1,0) -> 退く
A221: 220 | B221: 退ける | C221: どける | D221: THOÁI | E221: Đuổi khỏi, đuổi đi | F221: =+VLOOKUP(B221,'N2'!$A$2:$D$1287,1,0) -> 退ける
A222: 221 | B222: 被る | C222: かぶる | D222: BỊ | E222: Đội | F222: =+VLOOKUP(B222,'N2'!$A$2:$D$1287,1,0) -> 被る
A223: 222 | B223: 被せる | C223: かぶせる | D223: BỊ | E223: Phủ | F223: =+VLOOKUP(B223,'N2'!$A$2:$D$1287,1,0) -> 被せる
A224: 223 | B224: 齧る | C224: かじる | D224: NIẾT | E224: Cắn | F224: =+VLOOKUP(B224,'N2'!$A$2:$D$1287,1,0) -> 齧る
A225: 224 | B225: 撃つ | C225: うつ | D225: KÍCH | E225: Bắn (súng) | F225: =+VLOOKUP(B225,'N2'!$A$2:$D$1287,1,0) -> 撃つ
A226: 225 | B226: 漕ぐ | C226: こぐ | D226: TÀO | E226: Đạp xe | F226: =+VLOOKUP(B226,'N2'!$A$2:$D$1287,1,0) -> 漕ぐ
A227: 226 | B227: 敷く | C227: しく | D227: PHU | E227: Trải ra | F227: =+VLOOKUP(B227,'N2'!$A$2:$D$1287,1,0) -> 敷く
A228: 227 | B228: 床 | C228: ゆか | D228: SÀNG | E228: Nền nhà | F228: =+VLOOKUP(B228,'N2'!$A$2:$D$1287,1,0) -> #N/A
A229: 228 | B229: 注ぐ | C229: つぐ | D229: CHÚ | E229: Rót, trút, tưới | F229: =+VLOOKUP(B229,'N2'!$A$2:$D$1287,1,0) -> 注ぐ
A230: 229 | B230: 配る | C230: くばる | D230: PHỐI | E230: Phân phát | F230: =+VLOOKUP(B230,'N2'!$A$2:$D$1287,1,0) -> 配る
A231: 230 | B231: 配布 | C231: はいふ | D231: PHỐI BỐI | E231: Sự phân phát | F231: =+VLOOKUP(B231,'N2'!$A$2:$D$1287,1,0) -> 配布
... A251: 250 | B251: 躓く | C251: つまずく | D251: CHÍ | E251: Ngã, vấp | F251: =+VLOOKUP(B251,'N2'!$A$2:$D$1287,1,0) -> 躓く
A252: 251 | B252: ひく | C252: ひく | E252: Chèn | F252: =+VLOOKUP(B252,'N2'!$A$2:$D$1287,1,0) -> ひく
A253: 252 | B253: 骨折 | C253: こっせつ | D253: CỐT CHIẾT | E253: Gãy xương | F253: =+VLOOKUP(B253,'N2'!$A$2:$D$1287,1,0) -> #N/A
A254: 253 | B254: 骨 | C254: ほね | D254: CỐT | E254: Xương cốt, xương xẩu | F254: =+VLOOKUP(B254,'N2'!$A$2:$D$1287,1,0) -> #N/A
A255: 254 | B255: 死亡 | C255: しぼう | D255: TỬ VONG | E255: Tử vong, chết | F255: =+VLOOKUP(B255,'N2'!$A$2:$D$1287,1,0) -> #N/A
A256: 255 | B256: 溺れる | C256: おぼれる | D256: NỊCH | E256: Chìm, đắm, nghiện | F256: =+VLOOKUP(B256,'N2'!$A$2:$D$1287,1,0) -> 溺れる
A257: 256 | B257: 痛む | C257: いたむ | D257: THỐNG | E257: Đau | F257: =+VLOOKUP(B257,'N2'!$A$2:$D$1287,1,0) -> 痛む
A258: 257 | B258: かかる | C258: かかる | E258: Bị nhiễm | F258: =+VLOOKUP(B258,'N2'!$A$2:$D$1287,1,0) -> かかる
A259: 258 | B259: 酔う | C259: よう | D259: TỬU | E259: Say | F259: =+VLOOKUP(B259,'N2'!$A$2:$D$1287,1,0) -> 酔う
A260: 259 | B260: 吐く | C260: はく | D260: THỔ | E260: Thở ra, nôn ra | F260: =+VLOOKUP(B260,'N2'!$A$2:$D$1287,1,0) -> 吐く
A261: 260 | B261: 診る | C261: みる | D261: CHẨN | E261: Chẩn đoán, khám bệnh | F261: =+VLOOKUP(B261,'N2'!$A$2:$D$1287,1,0) -> 診る
A262: 261 | B262: 診察する | C262: しさつする | D262: CHẨN SÁT | E262: Chẩn đoán, khám bệnh | F262: =+VLOOKUP(B262,'N2'!$A$2:$D$1287,1,0) -> #N/A
A263: 262 | B263: 見舞う | C263: みまう | D263: KIẾN VŨ | E263: Đi thăm bệnh | F263: =+VLOOKUP(B263,'N2'!$A$2:$D$1287,1,0) -> 見舞う
A264: 263 | B264: 勤める | C264: つとめる | D264: CẦN | E264: Làm việc | F264: =+VLOOKUP(B264,'N2'!$A$2:$D$1287,1,0) -> 勤める
A265: 264 | B265: 勤務する | C265: きんむする | D265: CẦN VỤ | E265: Làm việc | F265: =+VLOOKUP(B265,'N2'!$A$2:$D$1287,1,0) -> #N/A
A266: 265 | B266: 稼ぐ | C266: かせぐ | D266: GIÁ | E266: Kiếm tiền | F266: =+VLOOKUP(B266,'N2'!$A$2:$D$1287,1,0) -> 稼ぐ
A267: 266 | B267: 学費 | C267: がくひ | D267: HỌC PHÍ | E267: Học phí | F267: =+VLOOKUP(B267,'N2'!$A$2:$D$1287,1,0) -> #N/A
A268: 267 | B268: 支払う | C268: しはらう | D268: CHI TRẢ | E268: Trả tiền | F268: =+VLOOKUP(B268,'N2'!$A$2:$D$1287,1,0) -> 支払う
A269: 268 | B269: 受け取る | C269: うけとる | D269: THỤ THỦ | E269: Nhận | F269: =+VLOOKUP(B269,'N2'!$A$2:$D$1287,1,0) -> 受け取る
A270: 269 | B270: 払い込む | C270: はらいこむ | D270: PHẤT VÀO | E270: Trả vào | F270: =+VLOOKUP(B270,'N2'!$A$2:$D$1287,1,0) -> 払い込む
... A387: 387 | B387: 分別 | C387: ぶんべつ | D387: PHÂN BIỆT | E387: Phân loại, phân biệt | F387: =+VLOOKUP(B387,'N2'!$A$2:$D$1287,1,0) -> 分別
A388: 388 | B388: しつこい | C388: しつこい | E388: Lằng nhằng, lèo nhèo | F388: =+VLOOKUP(B388,'N2'!$A$2:$D$1287,1,0) -> しつこい
A389: 389 | B389: 諄い | C389: くどい | D389: TRUÂN | E389: Dài dòng, lắm lời | F389: =+VLOOKUP(B389,'N2'!$A$2:$D$1287,1,0) -> #N/A
A390: 390 | B390: あっさりした | C390: あっさりした | E390: Đơn giản, cởi mở | F390: =+VLOOKUP(B390,'N2'!$A$2:$D$1287,1,0) -> #N/A
A391: 391 | B391: 煙い | C391: けむい | D391: YÊN | E391: Ngạt khói | F391: =+VLOOKUP(B391,'N2'!$A$2:$D$1287,1,0) -> 煙い
A392: 392 | B392: 煙たい | C392: けむたい | D392: YÊN | E392: Ngột ngạt | F392: =+VLOOKUP(B392,'N2'!$A$2:$D$1287,1,0) -> #N/A
A393: 393 | B393: 邪魔 | C393: じゃま | D393: TÀ MA | E393: Vướng víu | F393: =+VLOOKUP(B393,'N2'!$A$2:$D$1287,1,0) -> #N/A
A394: 394 | B394: 煩い | C394: うるさい | D394: PHIỀN | E394: Ồn ào | F394: =+VLOOKUP(B394,'N2'!$A$2:$D$1287,1,0) -> #N/A
A395: 395 | B395: 騒々しい | C395: そうぞうしい | D395: TAO | E395: Ồn ào | F395: =+VLOOKUP(B395,'N2'!$A$2:$D$1287,1,0) -> 騒々しい
A396: 396 | B396: 平穏 | C396: へいおん | D396: BÌNH ỔN | E396: Bình yên, bình tĩnh, yên bình | F396: =+VLOOKUP(B396,'N2'!$A$2:$D$1287,1,0) -> #N/A
A397: 397 | B397: 穏やか | C397: おだやか | D397: ỔN | E397: Điềm đảm, yên ả, ôn hòa | F397: =+VLOOKUP(B397,'N2'!$A$2:$D$1287,1,0) -> #N/A
A398: 398 | B398: 怒る | C398: おこる | D398: NỘ | E398: Tức giận | F398: =+VLOOKUP(B398,'N2'!$A$2:$D$1287,1,0) -> #N/A
A399: 399 | B399: 慌しい | C399: あわただしい | D399: HOẢNG | E399: Vội vã, cuống cuồng | F399: =+VLOOKUP(B399,'N2'!$A$2:$D$1287,1,0) -> #N/A
A400: 400 | B400: そそっかしい | C400: そそっかしい | E400: Hấp tấp; vội vàng; nôn nóng | F400: =+VLOOKUP(B400,'N2'!$A$2:$D$1287,1,0) -> そそっかしい
A401: 401 | B401: 思いがけない | C401: おもいがけない | D401: TƯ | E401: Không ngờ đến | F401: =+VLOOKUP(B401,'N2'!$A$2:$D$1287,1,0) -> 思いがけない
A402: 402 | B402: 何気ない | C402: なにげない | D402: HÀ KHÍ | E402: Không chủ ý, không cố ý | F402: =+VLOOKUP(B402,'N2'!$A$2:$D$1287,1,0) -> 何気ない
A403: 403 | B403: 傷つけ | C403: きずつけ | D403: THƯƠNG | E403: Tổn thương | F403: =+VLOOKUP(B403,'N2'!$A$2:$D$1287,1,0) -> #N/A
A404: 404 | B404: とんでもない | C404: とんでもない | E404: Không thể tin được, vớ vẩn | F404: =+VLOOKUP(B404,'N2'!$A$2:$D$1287,1,0) -> とんでもない
A405: 405 | B405: くだらない | C405: くだらない | E405: Không có giá trị, vô nghĩa | F405: =+VLOOKUP(B405,'N2'!$A$2:$D$1287,1,0) -> くだらない
A406: 406 | B406: 馬鹿馬鹿しい | C406: ばかばかしい | D406: MÃ LỘC | E406: Buồn cười, ngu ngốc | F406: =+VLOOKUP(B406,'N2'!$A$2:$D$1287,1,0) -> #N/A
A407: 407 | B407: 出鱈目 | C407: でたらめ | D407: XUẤT TUYẾT MỤC | E407: Bừa, linh tinh | F407: =+VLOOKUP(B407,'N2'!$A$2:$D$1287,1,0) -> #N/A
A408: 408 | B408: 偶然 | C408: ぐうぜん | D408: NGẪU NHIÊN | E408: Ngẫu nhiên | F408: =+VLOOKUP(B408,'N2'!$A$2:$D$1287,1,0) -> 偶然
A409: 409 | B409: いい加減 | C409: いいかげん | D409: GIA GIẢM | E409: Vô trách nhiệm, quá đáng | F409: =+VLOOKUP(B409,'N2'!$A$2:$D$1287,1,0) -> #N/A
A410: 410 | B410: だらしない | C410: だらしない | E410: Không gọn gàng | F410: =+VLOOKUP(B410,'N2'!$A$2:$D$1287,1,0) -> だらしない
A411: 411 | B411: 格好 | C411: かっこう | D411: CÁCH HẢO | E411: Ngoại hình, vẻ bề ngoài | F411: =+VLOOKUP(B411,'N2'!$A$2:$D$1287,1,0) -> #N/A
A412: 412 | B412: きちんとした | C412: きちんとした | E412: Gọn gàng, ngăn nắp | F412: =+VLOOKUP(B412,'N2'!$A$2:$D$1287,1,0) -> #N/A
A413: 413 | B413: 図々しい | C413: ずうずうしい | D413: ĐỒ | E413: Vô liêm sỉ, trơ trẽn | F413: =+VLOOKUP(B413,'N2'!$A$2:$D$1287,1,0) -> #N/A
A414: 414 | B414: 狡い | C414: ずるい | D414: GIẢO | E414: Láu cá, quỷ quyệt, không trung thực | F414: =+VLOOKUP(B414,'N2'!$A$2:$D$1287,1,0) -> 狡い
A415: 415 | B415: 憎らしい | C415: にくらしい | D415: TĂNG | E415: Đáng ghét, ghê tởm | F415: =+VLOOKUP(B415,'N2'!$A$2:$D$1287,1,0) -> 憎らしい
A416: 416 | B416: 憎い | C416: にくい | D416: TĂNG | E416: Căm thù, ghét | F416: =+VLOOKUP(B416,'N2'!$A$2:$D$1287,1,0) -> 憎い
...

Sheet Từ láy
B1: うとうと | C1: うとうと | D1: ngủ gật
B2: はらはら | C2: はらはら | D2: áy náy, run rẩy
B3: ぺらぺら | C3: ぺらぺら | D3: lưu loát, trôi chảy
B4: のろのろ | C4: のろのろ | D4: chậm chạp, lề mề
B5: ぼろぼろ | C5: ぼろぼろ | D5: rách tơi tả, te tua
B6: ますます | C6: ますます | D6: ngày càng, hơn nữa
B7: するする | C7: するする | D7: một cách trôi chảy, nhanh chóng
B8: とうとう | C8: とうとう | D8: cuối cùng, kết cục, sau cùng
B9: そわそわ | C9: そわそわ | D9: không yên, hoang mang
B10: まずまず | C10: まずまず | D10: kha khá, tàm tạm
B11: すらすら | C11: すらすら | D11: trơn chu, trôi chảy
B12: たびたび | C12: たびたび | D12: thường xuyên, lập lại nhiều lần
... B75: ぶらぶら | C75: ぶらぶら | D75: quanh quẩn, đung đưa (đồ vật)

Sheet Trợ từ
A1: 1 | B1: 非常 | C1: ひじょうに | D1: Rất
A2: 2 | B2: 大変（に） | C2: たいへん | D2: Cực
A3: 3 | B3: ほとんど | C3: ほとんど | D3: Gần như hoàn toàn
A4: 4 | B4: 大体 | C4: だいたい | D4: Đại khái
A5: 5 | B5: かなり | C5: かなり | D5: Khá
A6: 6 | B6: ずいぶん | C6: ずいぶん | D6: Khá
A7: 7 | B7: 結構 | C7: けっこう | D7: Khá, tốt, đủ
A8: 8 | B8: だいぶ だいぶん | C8: 大分 | D8: Hầu như
A9: 9 | B9: もっと | C9: もっと | D9: Hơn nữa
A10: 10 | B10: すっかり | C10: すっかり | D10: Toàn bộ
A11: 11 | B11: いっぱい | C11: いっぱい | D11: Đầy, nhiều
A12: 12 | B12: ぴったり | C12: ぴったり | D12: Vừa vặn, đúng
... A189: 189 | B189: いわゆる | C189: いわゆる | D189: gọi là, thường gọi là

Sheet bộ thủ
A1: BỘ THỦ | B1: TÊN BỘ | C1: Ý NGHĨA
A2: 一 | B2: nhất | C2: số một
A3: 〡 | B3: cổn | C3: nét sổ
A4: 丶 | B4: chủ | C4: nét phẩy
A5: 丿 | B5: phiệt | C5: nét sổ
A6: 乙 | B6: ất | C6: can thứ 2
A7: 亅 | B7: quyết | C7: nét móc
A8: 二 | B8: nhị | C8: số hai
A9: 亠 | B9: đầu | C9: bộ đầu
A10: 人 | B10: nhân | C10: người
A11: 亻 | B11: nhân đứng | C11: dùng để ghép
A12: 儿 | B12: nhi | C12: trẻ con
... A206: 色 | B206: sắc | C206: màu sắc

Sheet Sheet3
